Workbook

Sheet Overview
A1: Korea Scholarship Program: 30-Day Calendar
A2: Day 1 Fri 30 Oct 2026 to Day 30 Sat 28 Nov 2026 · two sessions a day: morning (8:30 to 11:30, or 9:00 to 12:00 on Anna days) and afternoon 1:00 to 4:30 · 11 students · Epic Campus
A3: Plan of 29 Oct: English Teacher 1 (Anna) teaches English 9:00 to 12:00 on Wed, Thu and Sat (12 days from 4 Nov), with Korean those afternoons. Other days: Korean mornings, English afternoons with Teacher 3. Week 1 (Days 1, 4, 5) is the grammar foundation with Teacher 2. Korean follows the 24 EStudykorea lessons and the 4 Korean workbooks. Budget and spending are on the Budget tab.
A5: Teaching hours by language
A6: Language | B6: Hours | C6: Share
A7: English | B7: =SUMIFS(Calendar!$H:$H,Calendar!$K:$K,"English") -> 105 | C7: =IFERROR(B7/SUM($B$7:$B$8),0) -> 0.54758801
A8: Korean | B8: =SUMIFS(Calendar!$H:$H,Calendar!$K:$K,"Korean") -> 86.75 | C8: =IFERROR(B8/SUM($B$7:$B$8),0) -> 0.45241199
A10: Hours by teacher
A11: Teacher | B11: Focus | C11: Confirmed | D11: Sessions | E11: Total hours | F11: Avg hours / day
A12: English Teacher 1 | B12: Anna. Wed, Thu & Sat 9:00 to 12:00: grammar & writing, speaking, mid and final tests, final presentations (12 days) | C12: Yes | D12: =COUNTIFS(Calendar!$L:$L,A12) -> 24 | E12: =SUMIFS(Calendar!$H:$H,Calendar!$L:$L,A12) -> 33 | F12: =E12/30 -> 1.1
A13: English Teacher 2 | B13: Week 1 grammar foundation + all mock interviews. Free Mon morning, Tue all day, Wed & Thu daytime. Not Saturdays, no evenings | C13: Yes | D13: =COUNTIFS(Calendar!$L:$L,A13) -> 13 | E13: =SUMIFS(Calendar!$H:$H,Calendar!$L:$L,A13) -> 24.75 | F13: =E13/30 -> 0.825
A14: English Teacher 3 | B14: English afternoons 1:00 to 4:30: reading, vocabulary, listening & IT lab | C14: Yes | D14: =COUNTIFS(Calendar!$L:$L,A14) -> 39 | E14: =SUMIFS(Calendar!$H:$H,Calendar!$L:$L,A14) -> 41 | F14: =E14/30 -> 1.3666667
A15: English Teacher 4 (TBC) | B15: Cover teacher if someone cannot come | C15: To be confirmed | D15: =COUNTIFS(Calendar!$L:$L,A15) -> 0 | E15: =SUMIFS(Calendar!$H:$H,Calendar!$L:$L,A15) -> 0 | F15: =E15/30 -> 0
A16: Korean Teacher 1 | B16: Korean mornings (staff) | C16: Yes | D16: =COUNTIFS(Calendar!$L:$L,A16) -> 30 | E16: =SUMIFS(Calendar!$H:$H,Calendar!$L:$L,A16) -> 41.25 | F16: =E16/30 -> 1.375
A17: Korean Teacher 2 | B17: Korean afternoons & Korean IT lab (staff) | C17: Yes | D17: =COUNTIFS(Calendar!$L:$L,A17) -> 42 | E17: =SUMIFS(Calendar!$H:$H,Calendar!$L:$L,A17) -> 45.5 | F17: =E17/30 -> 1.5166667
A20: Colour key
A21: English class
A22: Korean class
A23: IT lab
A24: Activity
A25: Test / interview
A26: Break
A27: Admin
A29: How to use
A30: • Calendar: every session, one row each. Filter by date, teacher or subject.
A31: • Grid: the whole program at a glance, one column per day. Good for printing.
A32: • Days: the theme and focus for each day, plus the IT lab task.
... A34: • To change a teacher, edit the Teacher column on Calendar; totals here update. The live version of this plan is the tracker on epicielts.live.

Sheet Budget
A1: Budget: Korea Scholarship Batch 1
A2: All amounts in LKR. Blue numbers are inputs you can change; black cells are formulas. Yellow cells still need a number. Record every payment on the Spending tab.
A4: 1. Income
A5: Item | B5: Amount | C5: Note
A6: Students | B6: 11 | C6: From Ishara, 28 Oct 2026: one more student added (was 10)
A7: Course fee per student | B7: 125000 | C7: From Ishara, 26 Oct 2026
A8: Total course fees | B8: =B6*B7 -> 1375000
A9: Campus share per student | B9: 25000 | C9: From Ishara: LKR 25,000 per student goes to the campus
A10: Campus share total | B10: =B6*B9 -> 275000
A11: Left to budget | B11: =B8-B10 -> 1100000 | C11: The percentages below are applied to this amount
A13: 2. Where the money goes
A14: Line | B14: % of budget | C14: Planned (LKR) | D14: Your figure (LKR) | E14: Spent so far (LKR) | F14: Left (LKR) | G14: Status
A15: Campus | B15: 0.1 | C15: =B15*$B$11 -> 110000 | D15: 100000 | E15: =SUMIFS(Spending!$D:$D,Spending!$B:$B,A15) -> 0 | F15: =D15-E15 -> 100000 | G15: =IF(E15>D15,"Overspent",IF(E15>=0.9*D15,"Nearly used","OK")) -> OK | H15: Percentages and amounts as given by Ishara, 26 Oct 2026
A16: Staff | B16: 0.4 | C16: =B16*$B$11 -> 440000 | D16: 400000 | E16: =SUMIFS(Spending!$D:$D,Spending!$B:$B,A16) -> 0 | F16: =D16-E16 -> 400000 | G16: =IF(E16>D16,"Overspent",IF(E16>=0.9*D16,"Nearly used","OK")) -> OK
A17: System | B17: 0.12 | C17: =B17*$B$11 -> 132000 | D17: 120000 | E17: =SUMIFS(Spending!$D:$D,Spending!$B:$B,A17) -> 0 | F17: =D17-E17 -> 120000 | G17: =IF(E17>D17,"Overspent",IF(E17>=0.9*D17,"Nearly used","OK")) -> OK
A18: Web | B18: 0.1 | C18: =B18*$B$11 -> 110000 | D18: 100000 | E18: =SUMIFS(Spending!$D:$D,Spending!$B:$B,A18) -> 0 | F18: =D18-E18 -> 100000 | G18: =IF(E18>D18,"Overspent",IF(E18>=0.9*D18,"Nearly used","OK")) -> OK
A19: Miscellaneous (transport and other) | B19: 0.1 | C19: =B19*$B$11 -> 110000 | D19: 100000 | E19: =SUMIFS(Spending!$D:$D,Spending!$B:$B,A19) -> 0 | F19: =D19-E19 -> 100000 | G19: =IF(E19>D19,"Overspent",IF(E19>=0.9*D19,"Nearly used","OK")) -> OK
A20: Accommodation and food | B20: 0.3 | C20: =B20*$B$11 -> 330000 | D20: 300000 | E20: =SUMIFS(Spending!$D:$D,Spending!$B:$B,A20) -> 18500 | F20: =D20-E20 -> 281500 | G20: =IF(E20>D20,"Overspent",IF(E20>=0.9*D20,"Nearly used","OK")) -> OK
A21: Total | B21: =SUM(B15:B20) -> 1.12 | C21: =SUM(C15:C20) -> 1232000 | D21: =SUM(D15:D20) -> 1120000 | E21: =SUM(E15:E20) -> 18500 | F21: =SUM(F15:F20) -> 1101500
A22: Check against the money left to budget | B22: =IF(ROUND(B21,4)=1,"Adds up to 100%","Adds up to "&TEXT(B21,"0%")&", not 100%") -> Adds up to 112%, not 100%
A23: Money left after your figures (negative = over budget) | B23: =B11-D21 -> -20000 | C23: Your six lines total more than the money left after the campus share. Lower the % or amounts (blue) until this is zero or positive.
A26: 3. Staff costs (inside the Staff line)
A27: Teacher | B27: Pay basis | C27: Rate (LKR) | D27: Units | E27: Cost (LKR) | F27: Status | G27: Hours in the plan | H27: Note | I27: Sessions (half days)
A28: English Teacher 1 | B28: Per session | C28: 5400 | D28: =IF(B28="Per hour",G28,IF(B28="Per month",$B$38,IF(B28="Per session",I28,0))) -> 12 | E28: =IFERROR(C28*D28,0) -> 64800 | F28: Agreed | G28: =SUMIFS(Calendar!$H:$H,Calendar!$L:$L,A28) -> 33 | H28: Anna. Wed, Thu & Sat 9:00 to 12:00. LKR 1,800 an hour x 3 hours = 5,400 a session. 12 sessions = 64,800 | I28: 12
A29: Transport: English Teacher 1 | B29: Per session | C29: 2600 | D29: =IF(B29="Per hour",G29,IF(B29="Per month",$B$38,IF(B29="Per session",I29,0))) -> 12 | E29: =IFERROR(C29*D29,0) -> 31200 | F29: Agreed | G29: =SUMIFS(Calendar!$H:$H,Calendar!$L:$L,A29) -> 0 | H29: Anna transport, LKR 2,600 a day x 12 days = 31,200 | I29: 12
A30: English Teacher 2 | B30: Per session | C30: 6000 | D30: =IF(B30="Per hour",G30,IF(B30="Per month",$B$38,IF(B30="Per session",I30,0))) -> 8 | E30: =IFERROR(C30*D30,0) -> 48000 | F30: Suggested | G30: =SUMIFS(Calendar!$H:$H,Calendar!$L:$L,A30) -> 24.75 | H30: Week 1 grammar + all mock interviews. Mix of 3 h and 3.5 h sessions. Suggested LKR 6,000 a session. Change when agreed | I30: 8
A31: English Teacher 3 | B31: Per month | C31: 55000 | D31: =IF(B31="Per hour",G31,IF(B31="Per month",$B$38,IF(B31="Per session",I31,0))) -> 1 | E31: =IFERROR(C31*D31,0) -> 55000 | F31: Confirmed | G31: =SUMIFS(Calendar!$H:$H,Calendar!$L:$L,A31) -> 41 | H31: From Ishara: LKR 55,000 per month, confirmed. English afternoons 1:00 to 4:30 (3.5 h) | I31: 14
A32: English Teacher 4 (TBC) | B32: Per session | C32: 5500 | D32: =IF(B32="Per hour",G32,IF(B32="Per month",$B$38,IF(B32="Per session",I32,0))) -> 0 | E32: =IFERROR(C32*D32,0) -> 0 | F32: Cover only | G32: =SUMIFS(Calendar!$H:$H,Calendar!$L:$L,A32) -> 0 | H32: Only paid if they cover a session. Enter sessions covered in column I | I32: 0
A33: Korean Teacher 1 | B33: Staff (no extra cost) | C33: 0 | D33: =IF(B33="Per hour",G33,IF(B33="Per month",$B$38,IF(B33="Per session",I33,0))) -> 0 | E33: =IFERROR(C33*D33,0) -> 0 | F33: Staff | G33: =SUMIFS(Calendar!$H:$H,Calendar!$L:$L,A33) -> 41.25 | H33: Campus staff | I33: 15
A34: Korean Teacher 2 | B34: Staff (no extra cost) | C34: 0 | D34: =IF(B34="Per hour",G34,IF(B34="Per month",$B$38,IF(B34="Per session",I34,0))) -> 0 | E34: =IFERROR(C34*D34,0) -> 0 | F34: Staff | G34: =SUMIFS(Calendar!$H:$H,Calendar!$L:$L,A34) -> 45.5 | H34: Campus staff | I34: 14
A35: Total staff cost | E35: =SUM(E28:E34) -> 199000
A36: Left in the Staff line | E36: =D16-E35 -> 201000
A38: Programme length in months (for monthly pay) | B38: 1 | C38: 30 teaching days = 1 month
A40: 4. Per student
A41: Item | B41: Amount (LKR)
A42: Food and accommodation per student per day | B42: =IFERROR(D20/B6/30,0) -> 909.09091
A43: Food and accommodation per student, whole programme | B43: =IFERROR(D20/B6,0) -> 27272.727
A44: Teaching cost per student (planned staff cost) | B44: =IFERROR(E35/B6,0) -> 18090.909
A45: Total budget per student (your figures + campus share) | B45: =IFERROR((D21+B10)/B6,0) -> 126818.18

Sheet Spending
A1: Spending log
A2: One row per payment. Choose the category from the list so the Budget tab adds it up. The first row is an example: replace or delete it.
A4: Date | B4: Category | C4: What it was for | D4: Amount (LKR) | E4: Paid by | F4: Receipt / note | H4: Total spent | I4: =SUM(D5:D204) -> 18500
A5: 46325 | B5: Accommodation and food | C5: Example: rice, vegetables and gas for week 1 | D5: 18500 | E5: Campus office | F5: Example row

Sheet Calendar
A1: Day | B1: Date | C1: Weekday | D1: Week | E1: Start | F1: End | G1: Time | H1: Hours | I1: Session | J1: Type | K1: Language | L1: Teacher | M1: Details
A2: 1 | B2: 46325 | C2: =TEXT(B2,"dddd") -> Friday | D2: =INT((A2-1)/6)+1 -> 1 | E2: 0.35416667 | F2: 0.375 | G2: =TEXT(E2,"h:mm")&" to "&TEXT(F2,"h:mm") -> 8:30 to 9:00 | H2: =ROUND((F2-E2)*24,2) -> 0.5 | I2: Welcome & orientation | J2: Admin | M2: Rules, timetable, rooms, site logins.
A3: 1 | B3: 46325 | C3: =TEXT(B3,"dddd") -> Friday | D3: =INT((A3-1)/6)+1 -> 1 | E3: 0.375 | F3: 0.44791667 | G3: =TEXT(E3,"h:mm")&" to "&TEXT(F3,"h:mm") -> 9:00 to 10:45 | H3: =ROUND((F3-E3)*24,2) -> 1.75 | I3: English placement test, parts 1 to 3 (IT lab) | J3: Test / interview | K3: English | M3: Grammar, vocabulary and reading; listening; writing. On epicielts.live (it opens on first login). Supervised by campus staff.
A4: 1 | B4: 46325 | C4: =TEXT(B4,"dddd") -> Friday | D4: =INT((A4-1)/6)+1 -> 1 | E4: 0.44791667 | F4: 0.45833333 | G4: =TEXT(E4,"h:mm")&" to "&TEXT(F4,"h:mm") -> 10:45 to 11:00 | H4: =ROUND((F4-E4)*24,2) -> 0.25 | I4: Tea break | J4: Break
A5: 1 | B5: 46325 | C5: =TEXT(B5,"dddd") -> Friday | D5: =INT((A5-1)/6)+1 -> 1 | E5: 0.45833333 | F5: 0.47916667 | G5: =TEXT(E5,"h:mm")&" to "&TEXT(F5,"h:mm") -> 11:00 to 11:30 | H5: =ROUND((F5-E5)*24,2) -> 0.5 | I5: Getting to know you | J5: Activity | K5: English | M5: Names, introductions, what the 30 days look like. Campus staff.
A6: 1 | B6: 46325 | C6: =TEXT(B6,"dddd") -> Friday | D6: =INT((A6-1)/6)+1 -> 1 | E6: 0.47916667 | F6: 0.54166667 | G6: =TEXT(E6,"h:mm")&" to "&TEXT(F6,"h:mm") -> 11:30 to 13:00 | H6: =ROUND((F6-E6)*24,2) -> 1.5 | I6: Lunch | J6: Break
A7: 1 | B7: 46325 | C7: =TEXT(B7,"dddd") -> Friday | D7: =INT((A7-1)/6)+1 -> 1 | E7: 0.54166667 | F7: 0.58333333 | G7: =TEXT(E7,"h:mm")&" to "&TEXT(F7,"h:mm") -> 13:00 to 14:00 | H7: =ROUND((F7-E7)*24,2) -> 1 | I7: Placement part 4: speaking (one by one) | J7: Test / interview | K7: English | L7: English Teacher 2 | M7: 5 minutes each. Students who are waiting start the parts of speech worksheet.
A8: 1 | B8: 46325 | C8: =TEXT(B8,"dddd") -> Friday | D8: =INT((A8-1)/6)+1 -> 1 | E8: 0.58333333 | F8: 0.59375 | G8: =TEXT(E8,"h:mm")&" to "&TEXT(F8,"h:mm") -> 14:00 to 14:15 | H8: =ROUND((F8-E8)*24,2) -> 0.25 | I8: Short break | J8: Break
A9: 1 | B9: 46325 | C9: =TEXT(B9,"dddd") -> Friday | D9: =INT((A9-1)/6)+1 -> 1 | E9: 0.59375 | F9: 0.6875 | G9: =TEXT(E9,"h:mm")&" to "&TEXT(F9,"h:mm") -> 14:15 to 16:30 | H9: =ROUND((F9-E9)*24,2) -> 2.25 | I9: Foundation 1: parts of speech | J9: English class | K9: English | L9: English Teacher 2 | M9: The 8 parts of speech: noun, pronoun, verb, adjective, adverb, preposition, conjunction, interjection. What each one does in a sentence. English workbook 1.
A10: 1 | B10: 46325 | C10: =TEXT(B10,"dddd") -> Friday | D10: =INT((A10-1)/6)+1 -> 1 | E10: 0.77083333 | F10: 0.8125 | G10: =TEXT(E10,"h:mm")&" to "&TEXT(F10,"h:mm") -> 18:30 to 19:30 | H10: =ROUND((F10-E10)*24,2) -> 1 | I10: Welcome night & icebreakers | J10: Activity | M10: Run by campus staff.
A11: 2 | B11: 46326 | C11: =TEXT(B11,"dddd") -> Saturday | D11: =INT((A11-1)/6)+1 -> 1 | E11: 0.35416667 | F11: 0.41666667 | G11: =TEXT(E11,"h:mm")&" to "&TEXT(F11,"h:mm") -> 8:30 to 10:00 | H11: =ROUND((F11-E11)*24,2) -> 1.5 | I11: Korean: Hangul 1: alphabet warm-up + How Hangul works | J11: Korean class | K11: Korean | L11: Korean Teacher 1 | M11: Korean workbook 1. Same lesson on the Korean site for the IT lab.
A12: 2 | B12: 46326 | C12: =TEXT(B12,"dddd") -> Saturday | D12: =INT((A12-1)/6)+1 -> 1 | E12: 0.41666667 | F12: 0.42708333 | G12: =TEXT(E12,"h:mm")&" to "&TEXT(F12,"h:mm") -> 10:00 to 10:15 | H12: =ROUND((F12-E12)*24,2) -> 0.25 | I12: Tea break | J12: Break
A13: 2 | B13: 46326 | C13: =TEXT(B13,"dddd") -> Saturday | D13: =INT((A13-1)/6)+1 -> 1 | E13: 0.42708333 | F13: 0.47916667 | G13: =TEXT(E13,"h:mm")&" to "&TEXT(F13,"h:mm") -> 10:15 to 11:30 | H13: =ROUND((F13-E13)*24,2) -> 1.25 | I13: Korean practice: Hangul 1: alphabet warm-up + How Hangul works | J13: Korean class | K13: Korean | L13: Korean Teacher 1 | M13: Korean workbook 1. Same lesson on the Korean site for the IT lab.
A14: 2 | B14: 46326 | C14: =TEXT(B14,"dddd") -> Saturday | D14: =INT((A14-1)/6)+1 -> 1 | E14: 0.47916667 | F14: 0.54166667 | G14: =TEXT(E14,"h:mm")&" to "&TEXT(F14,"h:mm") -> 11:30 to 13:00 | H14: =ROUND((F14-E14)*24,2) -> 1.5 | I14: Lunch | J14: Break
A15: 2 | B15: 46326 | C15: =TEXT(B15,"dddd") -> Saturday | D15: =INT((A15-1)/6)+1 -> 1 | E15: 0.54166667 | F15: 0.60416667 | G15: =TEXT(E15,"h:mm")&" to "&TEXT(F15,"h:mm") -> 13:00 to 14:30 | H15: =ROUND((F15-E15)*24,2) -> 1.5 | I15: Korean: Hangul 2: Six starting vowels | J15: Korean class | K15: Korean | L15: Korean Teacher 2 | M15: Korean workbook 1. Same lesson on the Korean site for the IT lab.
A16: 2 | B16: 46326 | C16: =TEXT(B16,"dddd") -> Saturday | D16: =INT((A16-1)/6)+1 -> 1 | E16: 0.60416667 | F16: 0.61458333 | G16: =TEXT(E16,"h:mm")&" to "&TEXT(F16,"h:mm") -> 14:30 to 14:45 | H16: =ROUND((F16-E16)*24,2) -> 0.25 | I16: Short break | J16: Break
A17: 2 | B17: 46326 | C17: =TEXT(B17,"dddd") -> Saturday | D17: =INT((A17-1)/6)+1 -> 1 | E17: 0.61458333 | F17: 0.64583333 | G17: =TEXT(E17,"h:mm")&" to "&TEXT(F17,"h:mm") -> 14:45 to 15:30 | H17: =ROUND((F17-E17)*24,2) -> 0.75 | I17: Korean practice: Hangul 2: Six starting vowels | J17: Korean class | K17: Korean | L17: Korean Teacher 2
A18: 2 | B18: 46326 | C18: =TEXT(B18,"dddd") -> Saturday | D18: =INT((A18-1)/6)+1 -> 1 | E18: 0.64583333 | F18: 0.6875 | G18: =TEXT(E18,"h:mm")&" to "&TEXT(F18,"h:mm") -> 15:30 to 16:30 | H18: =ROUND((F18-E18)*24,2) -> 1 | I18: IT lab: Korean practice | J18: IT lab | K18: Korean | L18: Korean Teacher 2 | M18: Korean: practise "Hangul 1: alphabet warm-up + How Hangul works" and "Hangul 2: Six starting vowels" on the Korean site.
A19: 3 | B19: 46327 | C19: =TEXT(B19,"dddd") -> Sunday | D19: =INT((A19-1)/6)+1 -> 1 | E19: 0.35416667 | F19: 0.41666667 | G19: =TEXT(E19,"h:mm")&" to "&TEXT(F19,"h:mm") -> 8:30 to 10:00 | H19: =ROUND((F19-E19)*24,2) -> 1.5 | I19: Korean: Hangul 3: The y-vowels | J19: Korean class | K19: Korean | L19: Korean Teacher 1 | M19: Korean workbook 1. Same lesson on the Korean site for the IT lab.
A20: 3 | B20: 46327 | C20: =TEXT(B20,"dddd") -> Sunday | D20: =INT((A20-1)/6)+1 -> 1 | E20: 0.41666667 | F20: 0.42708333 | G20: =TEXT(E20,"h:mm")&" to "&TEXT(F20,"h:mm") -> 10:00 to 10:15 | H20: =ROUND((F20-E20)*24,2) -> 0.25 | I20: Tea break | J20: Break
A21: 3 | B21: 46327 | C21: =TEXT(B21,"dddd") -> Sunday | D21: =INT((A21-1)/6)+1 -> 1 | E21: 0.42708333 | F21: 0.47916667 | G21: =TEXT(E21,"h:mm")&" to "&TEXT(F21,"h:mm") -> 10:15 to 11:30 | H21: =ROUND((F21-E21)*24,2) -> 1.25 | I21: Korean practice: Hangul 3: The y-vowels | J21: Korean class | K21: Korean | L21: Korean Teacher 1 | M21: Korean workbook 1. Same lesson on the Korean site for the IT lab.
A22: 3 | B22: 46327 | C22: =TEXT(B22,"dddd") -> Sunday | D22: =INT((A22-1)/6)+1 -> 1 | E22: 0.47916667 | F22: 0.54166667 | G22: =TEXT(E22,"h:mm")&" to "&TEXT(F22,"h:mm") -> 11:30 to 13:00 | H22: =ROUND((F22-E22)*24,2) -> 1.5 | I22: Lunch | J22: Break
A23: 3 | B23: 46327 | C23: =TEXT(B23,"dddd") -> Sunday | D23: =INT((A23-1)/6)+1 -> 1 | E23: 0.54166667 | F23: 0.60416667 | G23: =TEXT(E23,"h:mm")&" to "&TEXT(F23,"h:mm") -> 13:00 to 14:30 | H23: =ROUND((F23-E23)*24,2) -> 1.5 | I23: Korean: Hangul 4: Nine starting consonants | J23: Korean class | K23: Korean | L23: Korean Teacher 2 | M23: Korean workbook 1. Same lesson on the Korean site for the IT lab.
A24: 3 | B24: 46327 | C24: =TEXT(B24,"dddd") -> Sunday | D24: =INT((A24-1)/6)+1 -> 1 | E24: 0.60416667 | F24: 0.61458333 | G24: =TEXT(E24,"h:mm")&" to "&TEXT(F24,"h:mm") -> 14:30 to 14:45 | H24: =ROUND((F24-E24)*24,2) -> 0.25 | I24: Short break | J24: Break
A25: 3 | B25: 46327 | C25: =TEXT(B25,"dddd") -> Sunday | D25: =INT((A25-1)/6)+1 -> 1 | E25: 0.61458333 | F25: 0.64583333 | G25: =TEXT(E25,"h:mm")&" to "&TEXT(F25,"h:mm") -> 14:45 to 15:30 | H25: =ROUND((F25-E25)*24,2) -> 0.75 | I25: Korean practice: Hangul 4: Nine starting consonants | J25: Korean class | K25: Korean | L25: Korean Teacher 2
A26: 3 | B26: 46327 | C26: =TEXT(B26,"dddd") -> Sunday | D26: =INT((A26-1)/6)+1 -> 1 | E26: 0.64583333 | F26: 0.6875 | G26: =TEXT(E26,"h:mm")&" to "&TEXT(F26,"h:mm") -> 15:30 to 16:30 | H26: =ROUND((F26-E26)*24,2) -> 1 | I26: IT lab: Korean practice | J26: IT lab | K26: Korean | L26: Korean Teacher 2 | M26: Korean: practise "Hangul 3: The y-vowels" and "Hangul 4: Nine starting consonants" on the Korean site.
A27: 4 | B27: 46328 | C27: =TEXT(B27,"dddd") -> Monday | D27: =INT((A27-1)/6)+1 -> 1 | E27: 0.35416667 | F27: 0.41666667 | G27: =TEXT(E27,"h:mm")&" to "&TEXT(F27,"h:mm") -> 8:30 to 10:00 | H27: =ROUND((F27-E27)*24,2) -> 1.5 | I27: Foundation 2: sentence patterns (part 1) | J27: English class | K27: English | L27: English Teacher 2 | M27: How English sentences are built: subject + verb (+ object / complement / place). Word order, questions and negatives with be and do. English workbook 1.
A28: 4 | B28: 46328 | C28: =TEXT(B28,"dddd") -> Monday | D28: =INT((A28-1)/6)+1 -> 1 | E28: 0.41666667 | F28: 0.42708333 | G28: =TEXT(E28,"h:mm")&" to "&TEXT(F28,"h:mm") -> 10:00 to 10:15 | H28: =ROUND((F28-E28)*24,2) -> 0.25 | I28: Tea break | J28: Break
A29: 4 | B29: 46328 | C29: =TEXT(B29,"dddd") -> Monday | D29: =INT((A29-1)/6)+1 -> 1 | E29: 0.42708333 | F29: 0.47916667 | G29: =TEXT(E29,"h:mm")&" to "&TEXT(F29,"h:mm") -> 10:15 to 11:30 | H29: =ROUND((F29-E29)*24,2) -> 1.25 | I29: Foundation 2: sentence patterns (part 2: practice) | J29: English class | K29: English | L29: English Teacher 2 | M29: Build, speak and write sentences with today's patterns.
A30: 4 | B30: 46328 | C30: =TEXT(B30,"dddd") -> Monday | D30: =INT((A30-1)/6)+1 -> 1 | E30: 0.47916667 | F30: 0.54166667 | G30: =TEXT(E30,"h:mm")&" to "&TEXT(F30,"h:mm") -> 11:30 to 13:00 | H30: =ROUND((F30-E30)*24,2) -> 1.5 | I30: Lunch | J30: Break
A31: 4 | B31: 46328 | C31: =TEXT(B31,"dddd") -> Monday | D31: =INT((A31-1)/6)+1 -> 1 | E31: 0.54166667 | F31: 0.60416667 | G31: =TEXT(E31,"h:mm")&" to "&TEXT(F31,"h:mm") -> 13:00 to 14:30 | H31: =ROUND((F31-E31)*24,2) -> 1.5 | I31: Foundation 3: pronouns & prepositions (part 1) | J31: English class | K31: English | L31: English Teacher 3 | M31: Subject, object and possessive pronouns; this / that; prepositions of time (at, on, in) and place (in, on, under, next to, between). English workbook 1.
A32: 4 | B32: 46328 | C32: =TEXT(B32,"dddd") -> Monday | D32: =INT((A32-1)/6)+1 -> 1 | E32: 0.60416667 | F32: 0.61458333 | G32: =TEXT(E32,"h:mm")&" to "&TEXT(F32,"h:mm") -> 14:30 to 14:45 | H32: =ROUND((F32-E32)*24,2) -> 0.25 | I32: Short break | J32: Break
A33: 4 | B33: 46328 | C33: =TEXT(B33,"dddd") -> Monday | D33: =INT((A33-1)/6)+1 -> 1 | E33: 0.61458333 | F33: 0.64583333 | G33: =TEXT(E33,"h:mm")&" to "&TEXT(F33,"h:mm") -> 14:45 to 15:30 | H33: =ROUND((F33-E33)*24,2) -> 0.75 | I33: Foundation 3: pronouns & prepositions (part 2: practice) | J33: English class | K33: English | L33: English Teacher 3 | M33: Practice in pairs and on paper.
A34: 4 | B34: 46328 | C34: =TEXT(B34,"dddd") -> Monday | D34: =INT((A34-1)/6)+1 -> 1 | E34: 0.64583333 | F34: 0.6875 | G34: =TEXT(E34,"h:mm")&" to "&TEXT(F34,"h:mm") -> 15:30 to 16:30 | H34: =ROUND((F34-E34)*24,2) -> 1 | I34: IT lab: English practice | J34: IT lab | K34: English | L34: English Teacher 3 | M34: General English > Learn, grammar lessons; repeat today's worksheet tasks on screen.
A35: 5 | B35: 46329 | C35: =TEXT(B35,"dddd") -> Tuesday | D35: =INT((A35-1)/6)+1 -> 1 | E35: 0.35416667 | F35: 0.41666667 | G35: =TEXT(E35,"h:mm")&" to "&TEXT(F35,"h:mm") -> 8:30 to 10:00 | H35: =ROUND((F35-E35)*24,2) -> 1.5 | I35: Foundation 4: tenses (part 1) | J35: English class | K35: English | L35: English Teacher 2 | M35: The tense timeline: present simple and continuous, past simple, future (will / going to), a first look at present perfect. English workbook 1.
A36: 5 | B36: 46329 | C36: =TEXT(B36,"dddd") -> Tuesday | D36: =INT((A36-1)/6)+1 -> 1 | E36: 0.41666667 | F36: 0.42708333 | G36: =TEXT(E36,"h:mm")&" to "&TEXT(F36,"h:mm") -> 10:00 to 10:15 | H36: =ROUND((F36-E36)*24,2) -> 0.25 | I36: Tea break | J36: Break
A37: 5 | B37: 46329 | C37: =TEXT(B37,"dddd") -> Tuesday | D37: =INT((A37-1)/6)+1 -> 1 | E37: 0.42708333 | F37: 0.47916667 | G37: =TEXT(E37,"h:mm")&" to "&TEXT(F37,"h:mm") -> 10:15 to 11:30 | H37: =ROUND((F37-E37)*24,2) -> 1.25 | I37: Foundation 4: tenses (part 2: practice) | J37: English class | K37: English | L37: English Teacher 2 | M37: Build, speak and write sentences with today's patterns.
A38: 5 | B38: 46329 | C38: =TEXT(B38,"dddd") -> Tuesday | D38: =INT((A38-1)/6)+1 -> 1 | E38: 0.47916667 | F38: 0.54166667 | G38: =TEXT(E38,"h:mm")&" to "&TEXT(F38,"h:mm") -> 11:30 to 13:00 | H38: =ROUND((F38-E38)*24,2) -> 1.5 | I38: Lunch | J38: Break
A39: 5 | B39: 46329 | C39: =TEXT(B39,"dddd") -> Tuesday | D39: =INT((A39-1)/6)+1 -> 1 | E39: 0.54166667 | F39: 0.60416667 | G39: =TEXT(E39,"h:mm")&" to "&TEXT(F39,"h:mm") -> 13:00 to 14:30 | H39: =ROUND((F39-E39)*24,2) -> 1.5 | I39: Foundation 5: conjunctions & joining sentences (part 1) | J39: English class | K39: English | L39: English Teacher 2 | M39: and, but, or, so, because, when, before, after. Joining short sentences into longer ones. Week 1 review quiz. English workbook 1.
A40: 5 | B40: 46329 | C40: =TEXT(B40,"dddd") -> Tuesday | D40: =INT((A40-1)/6)+1 -> 1 | E40: 0.60416667 | F40: 0.61458333 | G40: =TEXT(E40,"h:mm")&" to "&TEXT(F40,"h:mm") -> 14:30 to 14:45 | H40: =ROUND((F40-E40)*24,2) -> 0.25 | I40: Short break | J40: Break
A41: 5 | B41: 46329 | C41: =TEXT(B41,"dddd") -> Tuesday | D41: =INT((A41-1)/6)+1 -> 1 | E41: 0.61458333 | F41: 0.64583333 | G41: =TEXT(E41,"h:mm")&" to "&TEXT(F41,"h:mm") -> 14:45 to 15:30 | H41: =ROUND((F41-E41)*24,2) -> 0.75 | I41: Foundation 5: conjunctions & joining sentences (part 2: practice) | J41: English class | K41: English | L41: English Teacher 2 | M41: Practice, then the week 1 review quiz.
A42: 5 | B42: 46329 | C42: =TEXT(B42,"dddd") -> Tuesday | D42: =INT((A42-1)/6)+1 -> 1 | E42: 0.64583333 | F42: 0.6875 | G42: =TEXT(E42,"h:mm")&" to "&TEXT(F42,"h:mm") -> 15:30 to 16:30 | H42: =ROUND((F42-E42)*24,2) -> 1 | I42: IT lab: English practice | J42: IT lab | K42: English | L42: English Teacher 2 | M42: General English > Learn, grammar lessons; repeat today's worksheet tasks on screen.
A43: 5 | B43: 46329 | C43: =TEXT(B43,"dddd") -> Tuesday | D43: =INT((A43-1)/6)+1 -> 1 | E43: 0.77083333 | F43: 0.8125 | G43: =TEXT(E43,"h:mm")&" to "&TEXT(F43,"h:mm") -> 18:30 to 19:30 | H43: =ROUND((F43-E43)*24,2) -> 1 | I43: Presentation night #1: "This is me" (2 min each) | J43: Activity | K43: English | M43: Run by campus staff. Students use the sentences they built in the week 1 foundation lessons.
A44: 6 | B44: 46330 | C44: =TEXT(B44,"dddd") -> Wednesday | D44: =INT((A44-1)/6)+1 -> 1 | E44: 0.35416667 | F44: 0.375 | G44: =TEXT(E44,"h:mm")&" to "&TEXT(F44,"h:mm") -> 8:30 to 9:00 | H44: =ROUND((F44-E44)*24,2) -> 0.5 | I44: Morning study time (self-study, campus staff) | J44: Activity | M44: Revise yesterday's workbook pages.
A45: 6 | B45: 46330 | C45: =TEXT(B45,"dddd") -> Wednesday | D45: =INT((A45-1)/6)+1 -> 1 | E45: 0.375 | F45: 0.4375 | G45: =TEXT(E45,"h:mm")&" to "&TEXT(F45,"h:mm") -> 9:00 to 10:30 | H45: =ROUND((F45-E45)*24,2) -> 1.5 | I45: English: Grammar & writing | J45: English class | K45: English | L45: English Teacher 1 | M45: Home & my town. there is / there are; prepositions of place. English workbook 2.
A46: 6 | B46: 46330 | C46: =TEXT(B46,"dddd") -> Wednesday | D46: =INT((A46-1)/6)+1 -> 1 | E46: 0.4375 | F46: 0.44791667 | G46: =TEXT(E46,"h:mm")&" to "&TEXT(F46,"h:mm") -> 10:30 to 10:45 | H46: =ROUND((F46-E46)*24,2) -> 0.25 | I46: Tea break | J46: Break
A47: 6 | B47: 46330 | C47: =TEXT(B47,"dddd") -> Wednesday | D47: =INT((A47-1)/6)+1 -> 1 | E47: 0.44791667 | F47: 0.5 | G47: =TEXT(E47,"h:mm")&" to "&TEXT(F47,"h:mm") -> 10:45 to 12:00 | H47: =ROUND((F47-E47)*24,2) -> 1.25 | I47: English: Speaking | J47: English class | K47: English | L47: English Teacher 1 | M47: Home & my town. Describe your home
A48: 6 | B48: 46330 | C48: =TEXT(B48,"dddd") -> Wednesday | D48: =INT((A48-1)/6)+1 -> 1 | E48: 0.5 | F48: 0.54166667 | G48: =TEXT(E48,"h:mm")&" to "&TEXT(F48,"h:mm") -> 12:00 to 13:00 | H48: =ROUND((F48-E48)*24,2) -> 1 | I48: Lunch | J48: Break
A49: 6 | B49: 46330 | C49: =TEXT(B49,"dddd") -> Wednesday | D49: =INT((A49-1)/6)+1 -> 1 | E49: 0.54166667 | F49: 0.60416667 | G49: =TEXT(E49,"h:mm")&" to "&TEXT(F49,"h:mm") -> 13:00 to 14:30 | H49: =ROUND((F49-E49)*24,2) -> 1.5 | I49: Korean: Hangul 5: Air and consonants | J49: Korean class | K49: Korean | L49: Korean Teacher 2 | M49: Korean workbook 1. Same lesson on the Korean site for the IT lab.
A50: 6 | B50: 46330 | C50: =TEXT(B50,"dddd") -> Wednesday | D50: =INT((A50-1)/6)+1 -> 1 | E50: 0.60416667 | F50: 0.61458333 | G50: =TEXT(E50,"h:mm")&" to "&TEXT(F50,"h:mm") -> 14:30 to 14:45 | H50: =ROUND((F50-E50)*24,2) -> 0.25 | I50: Short break | J50: Break
A51: 6 | B51: 46330 | C51: =TEXT(B51,"dddd") -> Wednesday | D51: =INT((A51-1)/6)+1 -> 1 | E51: 0.61458333 | F51: 0.64583333 | G51: =TEXT(E51,"h:mm")&" to "&TEXT(F51,"h:mm") -> 14:45 to 15:30 | H51: =ROUND((F51-E51)*24,2) -> 0.75 | I51: Korean practice: Hangul 5: Air and consonants | J51: Korean class | K51: Korean | L51: Korean Teacher 2
A52: 6 | B52: 46330 | C52: =TEXT(B52,"dddd") -> Wednesday | D52: =INT((A52-1)/6)+1 -> 1 | E52: 0.64583333 | F52: 0.6875 | G52: =TEXT(E52,"h:mm")&" to "&TEXT(F52,"h:mm") -> 15:30 to 16:30 | H52: =ROUND((F52-E52)*24,2) -> 1 | I52: IT lab: Korean practice | J52: IT lab | K52: Korean | L52: Korean Teacher 2 | M52: Korean: practise "Hangul 5: Air and consonants" on the Korean site.
A53: 7 | B53: 46331 | C53: =TEXT(B53,"dddd") -> Thursday | D53: =INT((A53-1)/6)+1 -> 2 | E53: 0.35416667 | F53: 0.375 | G53: =TEXT(E53,"h:mm")&" to "&TEXT(F53,"h:mm") -> 8:30 to 9:00 | H53: =ROUND((F53-E53)*24,2) -> 0.5 | I53: Morning study time (self-study, campus staff) | J53: Activity | M53: Revise yesterday's workbook pages.
A54: 7 | B54: 46331 | C54: =TEXT(B54,"dddd") -> Thursday | D54: =INT((A54-1)/6)+1 -> 2 | E54: 0.375 | F54: 0.4375 | G54: =TEXT(E54,"h:mm")&" to "&TEXT(F54,"h:mm") -> 9:00 to 10:30 | H54: =ROUND((F54-E54)*24,2) -> 1.5 | I54: English: Grammar & writing | J54: English class | K54: English | L54: English Teacher 1 | M54: Food & shopping. Countable / uncountable; some / any. English workbook 2.
A55: 7 | B55: 46331 | C55: =TEXT(B55,"dddd") -> Thursday | D55: =INT((A55-1)/6)+1 -> 2 | E55: 0.4375 | F55: 0.44791667 | G55: =TEXT(E55,"h:mm")&" to "&TEXT(F55,"h:mm") -> 10:30 to 10:45 | H55: =ROUND((F55-E55)*24,2) -> 0.25 | I55: Tea break | J55: Break
A56: 7 | B56: 46331 | C56: =TEXT(B56,"dddd") -> Thursday | D56: =INT((A56-1)/6)+1 -> 2 | E56: 0.44791667 | F56: 0.5 | G56: =TEXT(E56,"h:mm")&" to "&TEXT(F56,"h:mm") -> 10:45 to 12:00 | H56: =ROUND((F56-E56)*24,2) -> 1.25 | I56: English: Speaking | J56: English class | K56: English | L56: English Teacher 1 | M56: Food & shopping. Ordering in a café or restaurant
A57: 7 | B57: 46331 | C57: =TEXT(B57,"dddd") -> Thursday | D57: =INT((A57-1)/6)+1 -> 2 | E57: 0.5 | F57: 0.54166667 | G57: =TEXT(E57,"h:mm")&" to "&TEXT(F57,"h:mm") -> 12:00 to 13:00 | H57: =ROUND((F57-E57)*24,2) -> 1 | I57: Lunch | J57: Break
A58: 7 | B58: 46331 | C58: =TEXT(B58,"dddd") -> Thursday | D58: =INT((A58-1)/6)+1 -> 2 | E58: 0.54166667 | F58: 0.60416667 | G58: =TEXT(E58,"h:mm")&" to "&TEXT(F58,"h:mm") -> 13:00 to 14:30 | H58: =ROUND((F58-E58)*24,2) -> 1.5 | I58: Korean: Hangul 6: Tense consonants | J58: Korean class | K58: Korean | L58: Korean Teacher 2 | M58: Korean workbook 1. Same lesson on the Korean site for the IT lab.
A59: 7 | B59: 46331 | C59: =TEXT(B59,"dddd") -> Thursday | D59: =INT((A59-1)/6)+1 -> 2 | E59: 0.60416667 | F59: 0.61458333 | G59: =TEXT(E59,"h:mm")&" to "&TEXT(F59,"h:mm") -> 14:30 to 14:45 | H59: =ROUND((F59-E59)*24,2) -> 0.25 | I59: Short break | J59: Break
A60: 7 | B60: 46331 | C60: =TEXT(B60,"dddd") -> Thursday | D60: =INT((A60-1)/6)+1 -> 2 | E60: 0.61458333 | F60: 0.64583333 | G60: =TEXT(E60,"h:mm")&" to "&TEXT(F60,"h:mm") -> 14:45 to 15:30 | H60: =ROUND((F60-E60)*24,2) -> 0.75 | I60: Korean practice: Hangul 6: Tense consonants | J60: Korean class | K60: Korean | L60: Korean Teacher 2
A61: 7 | B61: 46331 | C61: =TEXT(B61,"dddd") -> Thursday | D61: =INT((A61-1)/6)+1 -> 2 | E61: 0.64583333 | F61: 0.6875 | G61: =TEXT(E61,"h:mm")&" to "&TEXT(F61,"h:mm") -> 15:30 to 16:30 | H61: =ROUND((F61-E61)*24,2) -> 1 | I61: IT lab: Korean practice | J61: IT lab | K61: Korean | L61: Korean Teacher 2 | M61: Korean: practise "Hangul 6: Tense consonants" on the Korean site.
A62: 8 | B62: 46332 | C62: =TEXT(B62,"dddd") -> Friday | D62: =INT((A62-1)/6)+1 -> 2 | E62: 0.35416667 | F62: 0.41666667 | G62: =TEXT(E62,"h:mm")&" to "&TEXT(F62,"h:mm") -> 8:30 to 10:00 | H62: =ROUND((F62-E62)*24,2) -> 1.5 | I62: Korean: Review: Hangul 1 to 6 + writing practice | J62: Korean class | K62: Korean | L62: Korean Teacher 1 | M62: Korean workbook 1. Same lesson on the Korean site for the IT lab.
A63: 8 | B63: 46332 | C63: =TEXT(B63,"dddd") -> Friday | D63: =INT((A63-1)/6)+1 -> 2 | E63: 0.41666667 | F63: 0.42708333 | G63: =TEXT(E63,"h:mm")&" to "&TEXT(F63,"h:mm") -> 10:00 to 10:15 | H63: =ROUND((F63-E63)*24,2) -> 0.25 | I63: Tea break | J63: Break
A64: 8 | B64: 46332 | C64: =TEXT(B64,"dddd") -> Friday | D64: =INT((A64-1)/6)+1 -> 2 | E64: 0.42708333 | F64: 0.47916667 | G64: =TEXT(E64,"h:mm")&" to "&TEXT(F64,"h:mm") -> 10:15 to 11:30 | H64: =ROUND((F64-E64)*24,2) -> 1.25 | I64: Korean practice: Review: Hangul 1 to 6 + writing practice | J64: Korean class | K64: Korean | L64: Korean Teacher 1 | M64: Korean workbook 1. Same lesson on the Korean site for the IT lab.
A65: 8 | B65: 46332 | C65: =TEXT(B65,"dddd") -> Friday | D65: =INT((A65-1)/6)+1 -> 2 | E65: 0.47916667 | F65: 0.54166667 | G65: =TEXT(E65,"h:mm")&" to "&TEXT(F65,"h:mm") -> 11:30 to 13:00 | H65: =ROUND((F65-E65)*24,2) -> 1.5 | I65: Lunch | J65: Break
A66: 8 | B66: 46332 | C66: =TEXT(B66,"dddd") -> Friday | D66: =INT((A66-1)/6)+1 -> 2 | E66: 0.54166667 | F66: 0.58333333 | G66: =TEXT(E66,"h:mm")&" to "&TEXT(F66,"h:mm") -> 13:00 to 14:00 | H66: =ROUND((F66-E66)*24,2) -> 1 | I66: English: Reading & vocabulary | J66: English class | K66: English | L66: English Teacher 3 | M66: Home & my town. Places in town. English workbook 2.
A67: 8 | B67: 46332 | C67: =TEXT(B67,"dddd") -> Friday | D67: =INT((A67-1)/6)+1 -> 2 | E67: 0.58333333 | F67: 0.59375 | G67: =TEXT(E67,"h:mm")&" to "&TEXT(F67,"h:mm") -> 14:00 to 14:15 | H67: =ROUND((F67-E67)*24,2) -> 0.25 | I67: Short break | J67: Break
A68: 8 | B68: 46332 | C68: =TEXT(B68,"dddd") -> Friday | D68: =INT((A68-1)/6)+1 -> 2 | E68: 0.59375 | F68: 0.63541667 | G68: =TEXT(E68,"h:mm")&" to "&TEXT(F68,"h:mm") -> 14:15 to 15:15 | H68: =ROUND((F68-E68)*24,2) -> 1 | I68: English: Listening | J68: English class | K68: English | L68: English Teacher 3 | M68: Home & my town. Following directions on a map
A69: 8 | B69: 46332 | C69: =TEXT(B69,"dddd") -> Friday | D69: =INT((A69-1)/6)+1 -> 2 | E69: 0.63541667 | F69: 0.64583333 | G69: =TEXT(E69,"h:mm")&" to "&TEXT(F69,"h:mm") -> 15:15 to 15:30 | H69: =ROUND((F69-E69)*24,2) -> 0.25 | I69: Short break | J69: Break
A70: 8 | B70: 46332 | C70: =TEXT(B70,"dddd") -> Friday | D70: =INT((A70-1)/6)+1 -> 2 | E70: 0.64583333 | F70: 0.6875 | G70: =TEXT(E70,"h:mm")&" to "&TEXT(F70,"h:mm") -> 15:30 to 16:30 | H70: =ROUND((F70-E70)*24,2) -> 1 | I70: IT lab: English practice | J70: IT lab | K70: English | L70: English Teacher 3 | M70: English: General English > Learn > "Home & my town", then its practice questions. Korean: practise "Review: Hangul 1 to 6 + writing practice" on the Korean site.
A71: 9 | B71: 46333 | C71: =TEXT(B71,"dddd") -> Saturday | D71: =INT((A71-1)/6)+1 -> 2 | E71: 0.35416667 | F71: 0.375 | G71: =TEXT(E71,"h:mm")&" to "&TEXT(F71,"h:mm") -> 8:30 to 9:00 | H71: =ROUND((F71-E71)*24,2) -> 0.5 | I71: Morning study time (self-study, campus staff) | J71: Activity | M71: Revise yesterday's workbook pages.
A72: 9 | B72: 46333 | C72: =TEXT(B72,"dddd") -> Saturday | D72: =INT((A72-1)/6)+1 -> 2 | E72: 0.375 | F72: 0.4375 | G72: =TEXT(E72,"h:mm")&" to "&TEXT(F72,"h:mm") -> 9:00 to 10:30 | H72: =ROUND((F72-E72)*24,2) -> 1.5 | I72: English: Grammar & writing | J72: English class | K72: English | L72: English Teacher 1 | M72: Now and last weekend. Present continuous vs present simple. English workbook 2.
A73: 9 | B73: 46333 | C73: =TEXT(B73,"dddd") -> Saturday | D73: =INT((A73-1)/6)+1 -> 2 | E73: 0.4375 | F73: 0.44791667 | G73: =TEXT(E73,"h:mm")&" to "&TEXT(F73,"h:mm") -> 10:30 to 10:45 | H73: =ROUND((F73-E73)*24,2) -> 0.25 | I73: Tea break | J73: Break
A74: 9 | B74: 46333 | C74: =TEXT(B74,"dddd") -> Saturday | D74: =INT((A74-1)/6)+1 -> 2 | E74: 0.44791667 | F74: 0.5 | G74: =TEXT(E74,"h:mm")&" to "&TEXT(F74,"h:mm") -> 10:45 to 12:00 | H74: =ROUND((F74-E74)*24,2) -> 1.25 | I74: English: Speaking | J74: English class | K74: English | L74: English Teacher 1 | M74: Now and last weekend. Describing a picture
A75: 9 | B75: 46333 | C75: =TEXT(B75,"dddd") -> Saturday | D75: =INT((A75-1)/6)+1 -> 2 | E75: 0.5 | F75: 0.54166667 | G75: =TEXT(E75,"h:mm")&" to "&TEXT(F75,"h:mm") -> 12:00 to 13:00 | H75: =ROUND((F75-E75)*24,2) -> 1 | I75: Lunch | J75: Break
A76: 9 | B76: 46333 | C76: =TEXT(B76,"dddd") -> Saturday | D76: =INT((A76-1)/6)+1 -> 2 | E76: 0.54166667 | F76: 0.60416667 | G76: =TEXT(E76,"h:mm")&" to "&TEXT(F76,"h:mm") -> 13:00 to 14:30 | H76: =ROUND((F76-E76)*24,2) -> 1.5 | I76: Korean: Hangul 7: Eleven more vowels | J76: Korean class | K76: Korean | L76: Korean Teacher 2 | M76: Korean workbook 2. Same lesson on the Korean site for the IT lab.
A77: 9 | B77: 46333 | C77: =TEXT(B77,"dddd") -> Saturday | D77: =INT((A77-1)/6)+1 -> 2 | E77: 0.60416667 | F77: 0.61458333 | G77: =TEXT(E77,"h:mm")&" to "&TEXT(F77,"h:mm") -> 14:30 to 14:45 | H77: =ROUND((F77-E77)*24,2) -> 0.25 | I77: Short break | J77: Break
A78: 9 | B78: 46333 | C78: =TEXT(B78,"dddd") -> Saturday | D78: =INT((A78-1)/6)+1 -> 2 | E78: 0.61458333 | F78: 0.64583333 | G78: =TEXT(E78,"h:mm")&" to "&TEXT(F78,"h:mm") -> 14:45 to 15:30 | H78: =ROUND((F78-E78)*24,2) -> 0.75 | I78: Korean practice: Hangul 7: Eleven more vowels | J78: Korean class | K78: Korean | L78: Korean Teacher 2
A79: 9 | B79: 46333 | C79: =TEXT(B79,"dddd") -> Saturday | D79: =INT((A79-1)/6)+1 -> 2 | E79: 0.64583333 | F79: 0.6875 | G79: =TEXT(E79,"h:mm")&" to "&TEXT(F79,"h:mm") -> 15:30 to 16:30 | H79: =ROUND((F79-E79)*24,2) -> 1 | I79: IT lab: Korean practice | J79: IT lab | K79: Korean | L79: Korean Teacher 2 | M79: Korean: practise "Hangul 7: Eleven more vowels" on the Korean site.
A80: 10 | B80: 46334 | C80: =TEXT(B80,"dddd") -> Sunday | D80: =INT((A80-1)/6)+1 -> 2 | E80: 0.35416667 | F80: 0.41666667 | G80: =TEXT(E80,"h:mm")&" to "&TEXT(F80,"h:mm") -> 8:30 to 10:00 | H80: =ROUND((F80-E80)*24,2) -> 1.5 | I80: Korean: Hangul 8: Build and write blocks | J80: Korean class | K80: Korean | L80: Korean Teacher 1 | M80: Korean workbook 2. Same lesson on the Korean site for the IT lab.
A81: 10 | B81: 46334 | C81: =TEXT(B81,"dddd") -> Sunday | D81: =INT((A81-1)/6)+1 -> 2 | E81: 0.41666667 | F81: 0.42708333 | G81: =TEXT(E81,"h:mm")&" to "&TEXT(F81,"h:mm") -> 10:00 to 10:15 | H81: =ROUND((F81-E81)*24,2) -> 0.25 | I81: Tea break | J81: Break
A82: 10 | B82: 46334 | C82: =TEXT(B82,"dddd") -> Sunday | D82: =INT((A82-1)/6)+1 -> 2 | E82: 0.42708333 | F82: 0.47916667 | G82: =TEXT(E82,"h:mm")&" to "&TEXT(F82,"h:mm") -> 10:15 to 11:30 | H82: =ROUND((F82-E82)*24,2) -> 1.25 | I82: Korean practice: Hangul 8: Build and write blocks | J82: Korean class | K82: Korean | L82: Korean Teacher 1 | M82: Korean workbook 2. Same lesson on the Korean site for the IT lab.
A83: 10 | B83: 46334 | C83: =TEXT(B83,"dddd") -> Sunday | D83: =INT((A83-1)/6)+1 -> 2 | E83: 0.47916667 | F83: 0.54166667 | G83: =TEXT(E83,"h:mm")&" to "&TEXT(F83,"h:mm") -> 11:30 to 13:00 | H83: =ROUND((F83-E83)*24,2) -> 1.5 | I83: Lunch | J83: Break
A84: 10 | B84: 46334 | C84: =TEXT(B84,"dddd") -> Sunday | D84: =INT((A84-1)/6)+1 -> 2 | E84: 0.54166667 | F84: 0.58333333 | G84: =TEXT(E84,"h:mm")&" to "&TEXT(F84,"h:mm") -> 13:00 to 14:00 | H84: =ROUND((F84-E84)*24,2) -> 1 | I84: English: Reading & vocabulary | J84: English class | K84: English | L84: English Teacher 3 | M84: Food & shopping. Clothes, prices and shops. English workbook 2.
A85: 10 | B85: 46334 | C85: =TEXT(B85,"dddd") -> Sunday | D85: =INT((A85-1)/6)+1 -> 2 | E85: 0.58333333 | F85: 0.59375 | G85: =TEXT(E85,"h:mm")&" to "&TEXT(F85,"h:mm") -> 14:00 to 14:15 | H85: =ROUND((F85-E85)*24,2) -> 0.25 | I85: Short break | J85: Break
A86: 10 | B86: 46334 | C86: =TEXT(B86,"dddd") -> Sunday | D86: =INT((A86-1)/6)+1 -> 2 | E86: 0.59375 | F86: 0.63541667 | G86: =TEXT(E86,"h:mm")&" to "&TEXT(F86,"h:mm") -> 14:15 to 15:15 | H86: =ROUND((F86-E86)*24,2) -> 1 | I86: English: Listening | J86: English class | K86: English | L86: English Teacher 3 | M86: Food & shopping. Week 2 review: a day in the city
A87: 10 | B87: 46334 | C87: =TEXT(B87,"dddd") -> Sunday | D87: =INT((A87-1)/6)+1 -> 2 | E87: 0.63541667 | F87: 0.64583333 | G87: =TEXT(E87,"h:mm")&" to "&TEXT(F87,"h:mm") -> 15:15 to 15:30 | H87: =ROUND((F87-E87)*24,2) -> 0.25 | I87: Short break | J87: Break
A88: 10 | B88: 46334 | C88: =TEXT(B88,"dddd") -> Sunday | D88: =INT((A88-1)/6)+1 -> 2 | E88: 0.64583333 | F88: 0.6875 | G88: =TEXT(E88,"h:mm")&" to "&TEXT(F88,"h:mm") -> 15:30 to 16:30 | H88: =ROUND((F88-E88)*24,2) -> 1 | I88: IT lab: English practice | J88: IT lab | K88: English | L88: English Teacher 3 | M88: English: General English > Learn > "Food & shopping", then its practice questions. Korean: practise "Hangul 8: Build and write blocks" on the Korean site.
A89: 11 | B89: 46335 | C89: =TEXT(B89,"dddd") -> Monday | D89: =INT((A89-1)/6)+1 -> 2 | E89: 0.35416667 | F89: 0.41666667 | G89: =TEXT(E89,"h:mm")&" to "&TEXT(F89,"h:mm") -> 8:30 to 10:00 | H89: =ROUND((F89-E89)*24,2) -> 1.5 | I89: Korean: Hangul 9: Final consonants: batchim | J89: Korean class | K89: Korean | L89: Korean Teacher 1 | M89: Korean workbook 2. Same lesson on the Korean site for the IT lab.
A90: 11 | B90: 46335 | C90: =TEXT(B90,"dddd") -> Monday | D90: =INT((A90-1)/6)+1 -> 2 | E90: 0.41666667 | F90: 0.42708333 | G90: =TEXT(E90,"h:mm")&" to "&TEXT(F90,"h:mm") -> 10:00 to 10:15 | H90: =ROUND((F90-E90)*24,2) -> 0.25 | I90: Tea break | J90: Break
A91: 11 | B91: 46335 | C91: =TEXT(B91,"dddd") -> Monday | D91: =INT((A91-1)/6)+1 -> 2 | E91: 0.42708333 | F91: 0.47916667 | G91: =TEXT(E91,"h:mm")&" to "&TEXT(F91,"h:mm") -> 10:15 to 11:30 | H91: =ROUND((F91-E91)*24,2) -> 1.25 | I91: Korean practice: Hangul 9: Final consonants: batchim | J91: Korean class | K91: Korean | L91: Korean Teacher 1 | M91: Korean workbook 2. Same lesson on the Korean site for the IT lab.
A92: 11 | B92: 46335 | C92: =TEXT(B92,"dddd") -> Monday | D92: =INT((A92-1)/6)+1 -> 2 | E92: 0.47916667 | F92: 0.54166667 | G92: =TEXT(E92,"h:mm")&" to "&TEXT(F92,"h:mm") -> 11:30 to 13:00 | H92: =ROUND((F92-E92)*24,2) -> 1.5 | I92: Lunch | J92: Break
A93: 11 | B93: 46335 | C93: =TEXT(B93,"dddd") -> Monday | D93: =INT((A93-1)/6)+1 -> 2 | E93: 0.54166667 | F93: 0.58333333 | G93: =TEXT(E93,"h:mm")&" to "&TEXT(F93,"h:mm") -> 13:00 to 14:00 | H93: =ROUND((F93-E93)*24,2) -> 1 | I93: English: Reading & vocabulary | J93: English class | K93: English | L93: English Teacher 3 | M93: Now and last weekend. Weekend activities. English workbook 2.
A94: 11 | B94: 46335 | C94: =TEXT(B94,"dddd") -> Monday | D94: =INT((A94-1)/6)+1 -> 2 | E94: 0.58333333 | F94: 0.59375 | G94: =TEXT(E94,"h:mm")&" to "&TEXT(F94,"h:mm") -> 14:00 to 14:15 | H94: =ROUND((F94-E94)*24,2) -> 0.25 | I94: Short break | J94: Break
A95: 11 | B95: 46335 | C95: =TEXT(B95,"dddd") -> Monday | D95: =INT((A95-1)/6)+1 -> 2 | E95: 0.59375 | F95: 0.63541667 | G95: =TEXT(E95,"h:mm")&" to "&TEXT(F95,"h:mm") -> 14:15 to 15:15 | H95: =ROUND((F95-E95)*24,2) -> 1 | I95: English: Listening | J95: English class | K95: English | L95: English Teacher 3 | M95: Now and last weekend. A weekend story
A96: 11 | B96: 46335 | C96: =TEXT(B96,"dddd") -> Monday | D96: =INT((A96-1)/6)+1 -> 2 | E96: 0.63541667 | F96: 0.64583333 | G96: =TEXT(E96,"h:mm")&" to "&TEXT(F96,"h:mm") -> 15:15 to 15:30 | H96: =ROUND((F96-E96)*24,2) -> 0.25 | I96: Short break | J96: Break
A97: 11 | B97: 46335 | C97: =TEXT(B97,"dddd") -> Monday | D97: =INT((A97-1)/6)+1 -> 2 | E97: 0.64583333 | F97: 0.6875 | G97: =TEXT(E97,"h:mm")&" to "&TEXT(F97,"h:mm") -> 15:30 to 16:30 | H97: =ROUND((F97-E97)*24,2) -> 1 | I97: IT lab: English practice | J97: IT lab | K97: English | L97: English Teacher 3 | M97: English: General English > Learn > "Now and last weekend", then its practice questions. Korean: practise "Hangul 9: Final consonants: batchim" on the Korean site.
A98: 11 | B98: 46335 | C98: =TEXT(B98,"dddd") -> Monday | D98: =INT((A98-1)/6)+1 -> 2 | E98: 0.77083333 | F98: 0.8125 | G98: =TEXT(E98,"h:mm")&" to "&TEXT(F98,"h:mm") -> 18:30 to 19:30 | H98: =ROUND((F98-E98)*24,2) -> 1 | I98: Debate night #1: City life or village life? | J98: Activity | K98: English | M98: Run by campus staff.
A99: 12 | B99: 46336 | C99: =TEXT(B99,"dddd") -> Tuesday | D99: =INT((A99-1)/6)+1 -> 2 | E99: 0.35416667 | F99: 0.41666667 | G99: =TEXT(E99,"h:mm")&" to "&TEXT(F99,"h:mm") -> 8:30 to 10:00 | H99: =ROUND((F99-E99)*24,2) -> 1.5 | I99: Korean: Hangul 10: Link sounds between blocks | J99: Korean class | K99: Korean | L99: Korean Teacher 1 | M99: Korean workbook 2. Same lesson on the Korean site for the IT lab.
A100: 12 | B100: 46336 | C100: =TEXT(B100,"dddd") -> Tuesday | D100: =INT((A100-1)/6)+1 -> 2 | E100: 0.41666667 | F100: 0.42708333 | G100: =TEXT(E100,"h:mm")&" to "&TEXT(F100,"h:mm") -> 10:00 to 10:15 | H100: =ROUND((F100-E100)*24,2) -> 0.25 | I100: Tea break | J100: Break
...

Sheet Grid
A1: Program at a glance
A3: Time | B3: Day 1 Fri 30 Oct | C3: Day 2 Sat 31 Oct | D3: Day 3 Sun 01 Nov | E3: Day 4 Mon 02 Nov | F3: Day 5 Tue 03 Nov | G3: Day 6 Wed 04 Nov | H3: Day 7 Thu 05 Nov | I3: Day 8 Fri 06 Nov | J3: Day 9 Sat 07 Nov | K3: Day 10 Sun 08 Nov | L3: Day 11 Mon 09 Nov | M3: Day 12 Tue 10 Nov | N3: Day 13 Wed 11 Nov | O3: Day 14 Thu 12 Nov | P3: Day 15 Fri 13 Nov | Q3: Day 16 Sat 14 Nov | R3: Day 17 Sun 15 Nov | S3: Day 18 Mon 16 Nov | T3: Day 19 Tue 17 Nov | U3: Day 20 Wed 18 Nov | V3: Day 21 Thu 19 Nov | W3: Day 22 Fri 20 Nov | X3: Day 23 Sat 21 Nov | Y3: Day 24 Sun 22 Nov | Z3: Day 25 Mon 23 Nov | AA3: Day 26 Tue 24 Nov | AB3: Day 27 Wed 25 Nov | AC3: Day 28 Thu 26 Nov | AD3: Day 29 Fri 27 Nov | AE3: Day 30 Sat 28 Nov
A4: 8:30 AM | B4: Welcome & orientation 8:30 to 9:00 | C4: Korean: Hangul 1: alphabet warm-up + How Hangul works 8:30 to 10:00 Korean Teacher 1 | D4: Korean: Hangul 3: The y-vowels 8:30 to 10:00 Korean Teacher 1 | E4: Foundation 2: sentence patterns (part 1) 8:30 to 10:00 English Teacher 2 | F4: Foundation 4: tenses (part 1) 8:30 to 10:00 English Teacher 2 | G4: Morning study time (self-study, campus staff) 8:30 to 9:00 | H4: Morning study time (self-study, campus staff) 8:30 to 9:00 | I4: Korean: Review: Hangul 1 to 6 + writing practice 8:30 to 10:00 Korean Teacher 1 | J4: Morning study time (self-study, campus staff) 8:30 to 9:00 | K4: Korean: Hangul 8: Build and write blocks 8:30 to 10:00 Korean Teacher 1 | L4: Korean: Hangul 9: Final consonants: batchim 8:30 to 10:00 Korean Teacher 1 | M4: Korean: Hangul 10: Link sounds between blocks 8:30 to 10:00 Korean Teacher 1 | N4: Morning study time (self-study, campus staff) 8:30 to 9:00 | O4: Morning study time (self-study, campus staff) 8:30 to 9:00 | P4: Korean: Hangul 12: Read words and sentences 8:30 to 10:00 Korean Teacher 1 | Q4: Morning study time (self-study, campus staff) 8:30 to 9:00 | R4: Korean: Beginner 1 lesson 2: What is this? 8:30 to 10:00 Korean Teacher 1 | S4: Korean: Beginner 1 lesson 3: Where is it? 8:30 to 10:00 Korean Teacher 1 | T4: Korean: Beginner 1 lesson 4: My everyday actions 8:30 to 10:00 Korean Teacher 1 | U4: Morning study time (self-study, campus staff) 8:30 to 9:00 | V4: Morning study time (self-study, campus staff) 8:30 to 9:00 | W4: Korean: Review: Beginner 1 lessons 1 to 6 8:30 to 10:00 Korean Teacher 1 | X4: Morning study time (self-study, campus staff) 8:30 to 9:00 | Y4: Korean: Beginner 1 lesson 8: Time & routines 8:30 to 10:00 Korean Teacher 1 | Z4: Korean: Beginner 1 lesson 9: What I do & do not do 8:30 to 10:00 Korean Teacher 1 | AA4: Korean: Beginner 1 lesson 10: What I did yesterday 8:30 to 10:00 Korean Teacher 1 | AB4: Morning study time (self-study, campus staff) 8:30 to 9:00 | AC4: Morning study time (self-study, campus staff) 8:30 to 9:00 | AD4: Korean: Beginner 1 lesson 12: Put it all together 8:30 to 10:00 Korean Teacher 1 | AE4: Morning study time (self-study, campus staff) 8:30 to 9:00
A5: 9:00 AM | B5: English placement test, parts 1 to 3 (IT lab) 9:00 to 10:45 | G5: English: Grammar & writing 9:00 to 10:30 English Teacher 1 | H5: English: Grammar & writing 9:00 to 10:30 English Teacher 1 | J5: English: Grammar & writing 9:00 to 10:30 English Teacher 1 | N5: English: Grammar & writing 9:00 to 10:30 English Teacher 1 | O5: Mid-programme English test: language & reading 9:00 to 10:30 English Teacher 1 | Q5: English: Grammar & writing 9:00 to 10:30 English Teacher 1 | U5: English: Grammar & writing 9:00 to 10:30 English Teacher 1 | V5: English: Grammar & writing 9:00 to 10:30 English Teacher 1 | X5: English: Grammar & writing 9:00 to 10:30 English Teacher 1 | AB5: English: Grammar & writing 9:00 to 10:30 English Teacher 1 | AC5: Final English test: language & reading 9:00 to 10:30 English Teacher 1 | AE5: Final English presentations (part 1) 9:00 to 10:30 English Teacher 1
A6: 10:00 AM | C6: Tea break | D6: Tea break | E6: Tea break | F6: Tea break | I6: Tea break | K6: Tea break | L6: Tea break | M6: Tea break | P6: Tea break | R6: Tea break | S6: Tea break | T6: Tea break | W6: Tea break | Y6: Tea break | Z6: Tea break | AA6: Tea break | AD6: Tea break
A7: 10:15 AM | C7: Korean practice: Hangul 1: alphabet warm-up + How Hangul works 10:15 to 11:30 Korean Teacher 1 | D7: Korean practice: Hangul 3: The y-vowels 10:15 to 11:30 Korean Teacher 1 | E7: Foundation 2: sentence patterns (part 2: practice) 10:15 to 11:30 English Teacher 2 | F7: Foundation 4: tenses (part 2: practice) 10:15 to 11:30 English Teacher 2 | I7: Korean practice: Review: Hangul 1 to 6 + writing practice 10:15 to 11:30 Korean Teacher 1 | K7: Korean practice: Hangul 8: Build and write blocks 10:15 to 11:30 Korean Teacher 1 | L7: Korean practice: Hangul 9: Final consonants: batchim 10:15 to 11:30 Korean Teacher 1 | M7: Korean practice: Hangul 10: Link sounds between blocks 10:15 to 11:30 Korean Teacher 1 | P7: Korean practice: Hangul 12: Read words and sentences 10:15 to 11:30 Korean Teacher 1 | R7: Korean practice: Beginner 1 lesson 2: What is this? 10:15 to 11:30 Korean Teacher 1 | S7: Korean practice: Beginner 1 lesson 3: Where is it? 10:15 to 11:30 Korean Teacher 1 | T7: Korean practice: Beginner 1 lesson 4: My everyday actions 10:15 to 11:30 Korean Teacher 1 | W7: Korean practice: Review: Beginner 1 lessons 1 to 6 10:15 to 11:30 Korean Teacher 1 | Y7: Korean practice: Beginner 1 lesson 8: Time & routines 10:15 to 11:30 Korean Teacher 1 | Z7: Korean practice: Beginner 1 lesson 9: What I do & do not do 10:15 to 11:30 Korean Teacher 1 | AA7: Korean practice: Beginner 1 lesson 10: What I did yesterday 10:15 to 11:30 Korean Teacher 1 | AD7: Korean practice: Beginner 1 lesson 12: Put it all together 10:15 to 11:30 Korean Teacher 1
A8: 10:30 AM | G8: Tea break | H8: Tea break | J8: Tea break | N8: Tea break | O8: Tea break | Q8: Tea break | U8: Tea break | V8: Tea break | X8: Tea break | AB8: Tea break | AC8: Tea break | AE8: Tea break
A9: 10:45 AM | B9: Tea break | G9: English: Speaking 10:45 to 12:00 English Teacher 1 | H9: English: Speaking 10:45 to 12:00 English Teacher 1 | J9: English: Speaking 10:45 to 12:00 English Teacher 1 | N9: English: Speaking 10:45 to 12:00 English Teacher 1 | O9: Mid-programme English test: writing 10:45 to 12:00 English Teacher 1 | Q9: English: Speaking 10:45 to 12:00 English Teacher 1 | U9: English: Speaking 10:45 to 12:00 English Teacher 1 | V9: English: Speaking 10:45 to 12:00 English Teacher 1 | X9: English: Speaking 10:45 to 12:00 English Teacher 1 | AB9: English: Speaking 10:45 to 12:00 English Teacher 1 | AC9: Final English test: writing 10:45 to 12:00 English Teacher 1 | AE9: Final English presentations (part 2) + programme review 10:45 to 12:00 English Teacher 1
A10: 11:00 AM | B10: Getting to know you 11:00 to 11:30
A11: 11:30 AM | B11: Lunch | C11: Lunch | D11: Lunch | E11: Lunch | F11: Lunch | I11: Lunch | K11: Lunch | L11: Lunch | M11: Lunch | P11: Lunch | R11: Lunch | S11: Lunch | T11: Lunch | W11: Lunch | Y11: Lunch | Z11: Lunch | AA11: Lunch | AD11: Lunch
A12: 12:00 PM | G12: Lunch | H12: Lunch | J12: Lunch | N12: Lunch | O12: Lunch | Q12: Lunch | U12: Lunch | V12: Lunch | X12: Lunch | AB12: Lunch | AC12: Lunch | AE12: Lunch
A13: 1:00 PM | B13: Placement part 4: speaking (one by one) 1:00 to 2:00 English Teacher 2 | C13: Korean: Hangul 2: Six starting vowels 1:00 to 2:30 Korean Teacher 2 | D13: Korean: Hangul 4: Nine starting consonants 1:00 to 2:30 Korean Teacher 2 | E13: Foundation 3: pronouns & prepositions (part 1) 1:00 to 2:30 English Teacher 3 | F13: Foundation 5: conjunctions & joining sentences (part 1) 1:00 to 2:30 English Teacher 2 | G13: Korean: Hangul 5: Air and consonants 1:00 to 2:30 Korean Teacher 2 | H13: Korean: Hangul 6: Tense consonants 1:00 to 2:30 Korean Teacher 2 | I13: English: Reading & vocabulary 1:00 to 2:00 English Teacher 3 | J13: Korean: Hangul 7: Eleven more vowels 1:00 to 2:30 Korean Teacher 2 | K13: English: Reading & vocabulary 1:00 to 2:00 English Teacher 3 | L13: English: Reading & vocabulary 1:00 to 2:00 English Teacher 3 | M13: English: Reading & vocabulary + Mock scholarship interview round 1 (side room) (English Teacher 2) 1:00 to 2:00 English Teacher 3 | N13: Korean: Hangul 11: Double finals and sound changes 1:00 to 2:30 Korean Teacher 2 | O13: Mid-programme English test: listening 1:00 to 2:00 English Teacher 3 | P13: Korean: Mid-programme Korean check (Hangul) 1:00 to 2:30 Korean Teacher 2 | Q13: Korean: Beginner 1 lesson 1: Greetings & introductions 1:00 to 2:30 Korean Teacher 2 | R13: English: Reading & vocabulary 1:00 to 2:00 English Teacher 3 | S13: English: Review & extra practice 1:00 to 2:30 English Teacher 3 | T13: English: Reading & vocabulary + Mock scholarship interview round 2 (side room) (English Teacher 2) 1:00 to 2:00 English Teacher 3 | U13: Korean: Beginner 1 lesson 5: Places & going out 1:00 to 2:30 Korean Teacher 2 | V13: Korean: Beginner 1 lesson 6: Numbers & prices 1:00 to 2:30 Korean Teacher 2 | W13: English: Reading & vocabulary 1:00 to 2:00 English Teacher 3 | X13: Korean: Beginner 1 lesson 7: Shopping & quantities 1:00 to 2:30 Korean Teacher 2 | Y13: English: Reading & vocabulary 1:00 to 2:00 English Teacher 3 | Z13: English: Reading & vocabulary 1:00 to 2:00 English Teacher 3 | AA13: English: Review & extra practice + Mock scholarship interview round 3 (side room) (English Teacher 2) 1:00 to 2:30 English Teacher 3 | AB13: Korean: Beginner 1 lesson 11: What I want to do 1:00 to 2:30 Korean Teacher 2 | AC13: Final English test: listening 1:00 to 2:00 English Teacher 3 | AD13: Korean: Final Korean test 1:00 to 2:30 Korean Teacher 2 | AE13: Korean: Korean self-introduction (graduation speech practice) 1:00 to 2:30 Korean Teacher 2
A14: 2:00 PM | B14: Short break | I14: Short break | K14: Short break | L14: Short break | M14: Short break | O14: Short break | R14: Short break | T14: Short break | W14: Short break | Y14: Short break | Z14: Short break | AC14: Short break
A15: 2:15 PM | B15: Foundation 1: parts of speech 2:15 to 4:30 English Teacher 2 | I15: English: Listening 2:15 to 3:15 English Teacher 3 | K15: English: Listening 2:15 to 3:15 English Teacher 3 | L15: English: Listening 2:15 to 3:15 English Teacher 3 | M15: English: Listening 2:15 to 3:15 English Teacher 3 | O15: Mid-programme test: speaking (one by one) + IT lab review 2:15 to 4:30 English Teacher 3 | R15: English: Listening 2:15 to 3:15 English Teacher 3 | T15: English: Listening 2:15 to 3:15 English Teacher 3 | W15: English: Listening 2:15 to 3:15 English Teacher 3 | Y15: English: Listening 2:15 to 3:15 English Teacher 3 | Z15: English: Listening 2:15 to 3:15 English Teacher 3 | AC15: Final mock interviews (counts as the final speaking test) 2:15 to 4:30 English Teacher 2
A16: 2:30 PM | C16: Short break | D16: Short break | E16: Short break | F16: Short break | G16: Short break | H16: Short break | J16: Short break | N16: Short break | P16: Short break | Q16: Short break | S16: Short break | U16: Short break | V16: Short break | X16: Short break | AA16: Short break | AB16: Short break | AD16: Short break | AE16: Short break
A17: 2:45 PM | C17: Korean practice: Hangul 2: Six starting vowels 2:45 to 3:30 Korean Teacher 2 | D17: Korean practice: Hangul 4: Nine starting consonants 2:45 to 3:30 Korean Teacher 2 | E17: Foundation 3: pronouns & prepositions (part 2: practice) 2:45 to 3:30 English Teacher 3 | F17: Foundation 5: conjunctions & joining sentences (part 2: practice) 2:45 to 3:30 English Teacher 2 | G17: Korean practice: Hangul 5: Air and consonants 2:45 to 3:30 Korean Teacher 2 | H17: Korean practice: Hangul 6: Tense consonants 2:45 to 3:30 Korean Teacher 2 | J17: Korean practice: Hangul 7: Eleven more vowels 2:45 to 3:30 Korean Teacher 2 | N17: Korean practice: Hangul 11: Double finals and sound changes 2:45 to 3:30 Korean Teacher 2 | P17: Mid-programme Korean check (Hangul) (continued) 2:45 to 3:30 Korean Teacher 2 | Q17: Korean practice: Beginner 1 lesson 1: Greetings & introductions 2:45 to 3:30 Korean Teacher 2 | S17: English: Speaking practice in pairs 2:45 to 3:30 English Teacher 3 | U17: Korean practice: Beginner 1 lesson 5: Places & going out 2:45 to 3:30 Korean Teacher 2 | V17: Korean practice: Beginner 1 lesson 6: Numbers & prices 2:45 to 3:30 Korean Teacher 2 | X17: Korean practice: Beginner 1 lesson 7: Shopping & quantities 2:45 to 3:30 Korean Teacher 2 | AA17: English: Speaking practice in pairs 2:45 to 3:30 English Teacher 3 | AB17: Korean practice: Beginner 1 lesson 11: What I want to do 2:45 to 3:30 Korean Teacher 2 | AD17: Final Korean test (continued) 2:45 to 3:30 Korean Teacher 2 | AE17: Korean practice: Korean self-introduction (graduation speech practice) 2:45 to 3:30 Korean Teacher 2
A18: 3:15 PM | I18: Short break | K18: Short break | L18: Short break | M18: Short break | R18: Short break | T18: Short break | W18: Short break | Y18: Short break | Z18: Short break
A19: 3:30 PM | C19: IT lab: Korean practice 3:30 to 4:30 Korean Teacher 2 | D19: IT lab: Korean practice 3:30 to 4:30 Korean Teacher 2 | E19: IT lab: English practice 3:30 to 4:30 English Teacher 3 | F19: IT lab: English practice 3:30 to 4:30 English Teacher 2 | G19: IT lab: Korean practice 3:30 to 4:30 Korean Teacher 2 | H19: IT lab: Korean practice 3:30 to 4:30 Korean Teacher 2 | I19: IT lab: English practice 3:30 to 4:30 English Teacher 3 | J19: IT lab: Korean practice 3:30 to 4:30 Korean Teacher 2 | K19: IT lab: English practice 3:30 to 4:30 English Teacher 3 | L19: IT lab: English practice 3:30 to 4:30 English Teacher 3 | M19: IT lab: English practice 3:30 to 4:30 English Teacher 3 | N19: IT lab: Korean practice 3:30 to 4:30 Korean Teacher 2 | P19: IT lab: Korean practice 3:30 to 4:30 Korean Teacher 2 | Q19: IT lab: Korean practice 3:30 to 4:30 Korean Teacher 2 | R19: IT lab: English practice 3:30 to 4:30 English Teacher 3 | S19: IT lab: English practice 3:30 to 4:30 English Teacher 3 | T19: IT lab: English practice 3:30 to 4:30 English Teacher 3 | U19: IT lab: Korean practice 3:30 to 4:30 Korean Teacher 2 | V19: IT lab: Korean practice 3:30 to 4:30 Korean Teacher 2 | W19: IT lab: English practice 3:30 to 4:30 English Teacher 3 | X19: IT lab: Korean practice 3:30 to 4:30 Korean Teacher 2 | Y19: IT lab: English practice 3:30 to 4:30 English Teacher 3 | Z19: IT lab: English practice 3:30 to 4:30 English Teacher 3 | AA19: IT lab: English practice 3:30 to 4:30 English Teacher 3 | AB19: IT lab: Korean practice 3:30 to 4:30 Korean Teacher 2 | AD19: IT lab: Korean practice 3:30 to 4:30 Korean Teacher 2 | AE19: IT lab: Korean practice 3:30 to 4:30 Korean Teacher 2
A20: 6:30 PM | B20: Welcome night & icebreakers 6:30 to 7:30 | F20: Presentation night #1: "This is me" (2 min each) 6:30 to 7:30 | L20: Debate night #1: City life or village life? 6:30 to 7:30 | R20: Presentation night #2: "My best memory" 6:30 to 7:30 | X20: Debate night #2: Is studying abroad worth it? 6:30 to 7:30 | AE20: Graduation ceremony & certificates 6:30 to 7:30

Sheet Days
A1: Day | B1: Date | C1: Week | D1: Theme | E1: English focus | F1: Korean focus (suggested) | G1: IT lab task
A2: 1 | B2: 46325 | C2: =INT((A2-1)/6)+1 -> 1 | D2: Welcome + placement test + Placement speaking + Foundation 1 | E2: Morning: Welcome + placement test Afternoon: Placement speaking + Foundation 1 | F2: No Korean today | G2: English: General English > Learn, revise this week's lessons.
A3: 2 | B3: 46326 | C3: =INT((A3-1)/6)+1 -> 1 | D3: Korean day: Hangul 1: alphabet warm-up + How Hangul works | E3: No English today | F3: Morning: Hangul 1: alphabet warm-up + How Hangul works Afternoon: Hangul 2: Six starting vowels | G3: Korean: practise "Hangul 1: alphabet warm-up + How Hangul works" and "Hangul 2: Six starting vowels" on the Korean site.
A4: 3 | B4: 46327 | C4: =INT((A4-1)/6)+1 -> 1 | D4: Korean day: Hangul 3: The y-vowels | E4: No English today | F4: Morning: Hangul 3: The y-vowels Afternoon: Hangul 4: Nine starting consonants | G4: Korean: practise "Hangul 3: The y-vowels" and "Hangul 4: Nine starting consonants" on the Korean site.
A5: 4 | B5: 46328 | C5: =INT((A5-1)/6)+1 -> 1 | D5: Foundation 2: sentence patterns + Foundation 3: pronouns & prepositions | E5: Morning: Foundation 2: sentence patterns Afternoon: Foundation 3: pronouns & prepositions | F5: No Korean today | G5: English: General English > Learn, revise this week's lessons.
A6: 5 | B6: 46329 | C6: =INT((A6-1)/6)+1 -> 1 | D6: Foundation 4: tenses + Foundation 5: conjunctions & joining sentences | E6: Morning: Foundation 4: tenses Afternoon: Foundation 5: conjunctions & joining sentences | F6: No Korean today | G6: English: General English > Learn, revise this week's lessons.
A7: 6 | B7: 46330 | C7: =INT((A7-1)/6)+1 -> 1 | D7: Home & my town (grammar, writing & speaking) | E7: Morning: Home & my town (grammar, writing & speaking) | F7: Afternoon: Hangul 5: Air and consonants | G7: Korean: practise "Hangul 5: Air and consonants" on the Korean site.
A8: 7 | B8: 46331 | C8: =INT((A8-1)/6)+1 -> 2 | D8: Food & shopping (grammar, writing & speaking) | E8: Morning: Food & shopping (grammar, writing & speaking) | F8: Afternoon: Hangul 6: Tense consonants | G8: Korean: practise "Hangul 6: Tense consonants" on the Korean site.
A9: 8 | B9: 46332 | C9: =INT((A9-1)/6)+1 -> 2 | D9: Home & my town (reading & listening) | E9: Afternoon: Home & my town (reading & listening) | F9: Morning: Review: Hangul 1 to 6 + writing practice | G9: English: General English > Learn > "Home & my town", then its practice questions. Korean: practise "Review: Hangul 1 to 6 + writing practice" on the Korean site.
A10: 9 | B10: 46333 | C10: =INT((A10-1)/6)+1 -> 2 | D10: Now and last weekend (grammar, writing & speaking) | E10: Morning: Now and last weekend (grammar, writing & speaking) | F10: Afternoon: Hangul 7: Eleven more vowels | G10: Korean: practise "Hangul 7: Eleven more vowels" on the Korean site.
A11: 10 | B11: 46334 | C11: =INT((A11-1)/6)+1 -> 2 | D11: Food & shopping (reading & listening) | E11: Afternoon: Food & shopping (reading & listening) | F11: Morning: Hangul 8: Build and write blocks | G11: English: General English > Learn > "Food & shopping", then its practice questions. Korean: practise "Hangul 8: Build and write blocks" on the Korean site.
A12: 11 | B12: 46335 | C12: =INT((A12-1)/6)+1 -> 2 | D12: Now and last weekend (reading & listening) | E12: Afternoon: Now and last weekend (reading & listening) | F12: Morning: Hangul 9: Final consonants: batchim | G12: English: General English > Learn > "Now and last weekend", then its practice questions. Korean: practise "Hangul 9: Final consonants: batchim" on the Korean site.
A13: 12 | B13: 46336 | C13: =INT((A13-1)/6)+1 -> 2 | D13: Yesterday & school (reading & listening) | E13: Afternoon: Yesterday & school (reading & listening) | F13: Morning: Hangul 10: Link sounds between blocks | G13: English: General English > Learn > "Yesterday & school", then its practice questions. Korean: practise "Hangul 10: Link sounds between blocks" on the Korean site.
... A31: 30 | B31: 46354 | C31: =INT((A31-1)/6)+1 -> 5 | D31: Final English presentations | E31: Morning: Final English presentations | F31: Afternoon: Korean self-introduction (graduation speech practice) | G31: Korean: practise "Korean self-introduction (graduation speech practice)" on the Korean site.

Sheet English Teacher 1
A1: English Teacher 1
A2: Anna. Wed, Thu & Sat 9:00 to 12:00: grammar & writing, speaking, mid and final tests, final presentations (12 days) · Confirmed
A3: Sessions: | B3: =COUNT(A6:A17) -> 12 | D3: Hours: | E3: =SUM(F6:F17) -> 36 | G3: One row per session. Hours = start to finish, including the tea break.
A5: Day | B5: Date | C5: Session | D5: Start | E5: End | F5: Hours | G5: What happens in this session | H5: Type
A6: 6 | B6: 46330 | C6: Morning | D6: 0.375 | E6: 0.5 | F6: =ROUND((E6-D6)*24,2) -> 3 | G6: 9:00 to 10:30 English: Grammar & writing 10:45 to 12:00 English: Speaking | H6: English class
A7: 7 | B7: 46331 | C7: Morning | D7: 0.375 | E7: 0.5 | F7: =ROUND((E7-D7)*24,2) -> 3 | G7: 9:00 to 10:30 English: Grammar & writing 10:45 to 12:00 English: Speaking | H7: English class
A8: 9 | B8: 46333 | C8: Morning | D8: 0.375 | E8: 0.5 | F8: =ROUND((E8-D8)*24,2) -> 3 | G8: 9:00 to 10:30 English: Grammar & writing 10:45 to 12:00 English: Speaking | H8: English class
A9: 13 | B9: 46337 | C9: Morning | D9: 0.375 | E9: 0.5 | F9: =ROUND((E9-D9)*24,2) -> 3 | G9: 9:00 to 10:30 English: Grammar & writing 10:45 to 12:00 English: Speaking | H9: English class
A10: 14 | B10: 46338 | C10: Morning | D10: 0.375 | E10: 0.5 | F10: =ROUND((E10-D10)*24,2) -> 3 | G10: 9:00 to 10:30 Mid-programme English test: language & reading 10:45 to 12:00 Mid-programme English test: writing | H10: Test / interview
A11: 16 | B11: 46340 | C11: Morning | D11: 0.375 | E11: 0.5 | F11: =ROUND((E11-D11)*24,2) -> 3 | G11: 9:00 to 10:30 English: Grammar & writing 10:45 to 12:00 English: Speaking | H11: English class
A12: 20 | B12: 46344 | C12: Morning | D12: 0.375 | E12: 0.5 | F12: =ROUND((E12-D12)*24,2) -> 3 | G12: 9:00 to 10:30 English: Grammar & writing 10:45 to 12:00 English: Speaking | H12: English class
A13: 21 | B13: 46345 | C13: Morning | D13: 0.375 | E13: 0.5 | F13: =ROUND((E13-D13)*24,2) -> 3 | G13: 9:00 to 10:30 English: Grammar & writing 10:45 to 12:00 English: Speaking | H13: English class
A14: 23 | B14: 46347 | C14: Morning | D14: 0.375 | E14: 0.5 | F14: =ROUND((E14-D14)*24,2) -> 3 | G14: 9:00 to 10:30 English: Grammar & writing 10:45 to 12:00 English: Speaking | H14: English class
A15: 27 | B15: 46351 | C15: Morning | D15: 0.375 | E15: 0.5 | F15: =ROUND((E15-D15)*24,2) -> 3 | G15: 9:00 to 10:30 English: Grammar & writing 10:45 to 12:00 English: Speaking | H15: English class
A16: 28 | B16: 46352 | C16: Morning | D16: 0.375 | E16: 0.5 | F16: =ROUND((E16-D16)*24,2) -> 3 | G16: 9:00 to 10:30 Final English test: language & reading 10:45 to 12:00 Final English test: writing | H16: Test / interview
A17: 30 | B17: 46354 | C17: Morning | D17: 0.375 | E17: 0.5 | F17: =ROUND((E17-D17)*24,2) -> 3 | G17: 9:00 to 10:30 Final English presentations (part 1) 10:45 to 12:00 Final English presentations (part 2) + programme review | H17: Activity

Sheet English Teacher 2
A1: English Teacher 2
A2: Week 1 grammar foundation + all mock interviews. Free Mon morning, Tue all day, Wed & Thu daytime. Not Saturdays, no evenings · Confirmed
A3: Sessions: | B3: =COUNT(A6:A13) -> 8 | D3: Hours: | E3: =SUM(F6:F13) -> 25.75 | G3: One row per session. Hours = start to finish, including the tea break. Mock interviews run in a side room during Teacher 3's afternoon.
A5: Day | B5: Date | C5: Session | D5: Start | E5: End | F5: Hours | G5: What happens in this session | H5: Type
A6: 1 | B6: 46325 | C6: Afternoon | D6: 0.54166667 | E6: 0.6875 | F6: =ROUND((E6-D6)*24,2) -> 3.5 | G6: 1:00 to 2:00 Placement part 4: speaking (one by one) 2:15 to 4:30 Foundation 1: parts of speech | H6: English class + Test / interview
A7: 4 | B7: 46328 | C7: Morning | D7: 0.35416667 | E7: 0.47916667 | F7: =ROUND((E7-D7)*24,2) -> 3 | G7: 8:30 to 10:00 Foundation 2: sentence patterns (part 1) 10:15 to 11:30 Foundation 2: sentence patterns (part 2: practice) | H7: English class
A8: 5 | B8: 46329 | C8: Morning | D8: 0.35416667 | E8: 0.47916667 | F8: =ROUND((E8-D8)*24,2) -> 3 | G8: 8:30 to 10:00 Foundation 4: tenses (part 1) 10:15 to 11:30 Foundation 4: tenses (part 2: practice) | H8: English class
A9: 5 | B9: 46329 | C9: Afternoon | D9: 0.54166667 | E9: 0.6875 | F9: =ROUND((E9-D9)*24,2) -> 3.5 | G9: 1:00 to 2:30 Foundation 5: conjunctions & joining sentences (part 1) 2:45 to 3:30 Foundation 5: conjunctions & joining sentences (part 2: practice) 3:30 to 4:30 IT lab: English practice | H9: English class + IT lab
A10: 12 | B10: 46336 | C10: Afternoon | D10: 0.54166667 | E10: 0.6875 | F10: =ROUND((E10-D10)*24,2) -> 3.5 | G10: 1:00 to 4:30 Mock scholarship interview round 1 (side room) | H10: Test / interview
A11: 19 | B11: 46343 | C11: Afternoon | D11: 0.54166667 | E11: 0.6875 | F11: =ROUND((E11-D11)*24,2) -> 3.5 | G11: 1:00 to 4:30 Mock scholarship interview round 2 (side room) | H11: Test / interview
A12: 26 | B12: 46350 | C12: Afternoon | D12: 0.54166667 | E12: 0.6875 | F12: =ROUND((E12-D12)*24,2) -> 3.5 | G12: 1:00 to 4:30 Mock scholarship interview round 3 (side room) | H12: Test / interview
A13: 28 | B13: 46352 | C13: Afternoon | D13: 0.59375 | E13: 0.6875 | F13: =ROUND((E13-D13)*24,2) -> 2.25 | G13: 2:15 to 4:30 Final mock interviews (counts as the final speaking test) | H13: Test / interview

Sheet English Teacher 3
A1: English Teacher 3
A2: English afternoons 1:00 to 4:30: reading, vocabulary, listening & IT lab · Confirmed
A3: Sessions: | B3: =COUNT(A6:A19) -> 14 | D3: Hours: | E3: =SUM(F6:F19) -> 46.5 | G3: One row per session. Hours = start to finish, including the tea break.
A5: Day | B5: Date | C5: Session | D5: Start | E5: End | F5: Hours | G5: What happens in this session | H5: Type
A6: 4 | B6: 46328 | C6: Afternoon | D6: 0.54166667 | E6: 0.6875 | F6: =ROUND((E6-D6)*24,2) -> 3.5 | G6: 1:00 to 2:30 Foundation 3: pronouns & prepositions (part 1) 2:45 to 3:30 Foundation 3: pronouns & prepositions (part 2: practice) 3:30 to 4:30 IT lab: English practice | H6: English class + IT lab
A7: 8 | B7: 46332 | C7: Afternoon | D7: 0.54166667 | E7: 0.6875 | F7: =ROUND((E7-D7)*24,2) -> 3.5 | G7: 1:00 to 2:00 English: Reading & vocabulary 2:15 to 3:15 English: Listening 3:30 to 4:30 IT lab: English practice | H7: English class + IT lab
A8: 10 | B8: 46334 | C8: Afternoon | D8: 0.54166667 | E8: 0.6875 | F8: =ROUND((E8-D8)*24,2) -> 3.5 | G8: 1:00 to 2:00 English: Reading & vocabulary 2:15 to 3:15 English: Listening 3:30 to 4:30 IT lab: English practice | H8: English class + IT lab
A9: 11 | B9: 46335 | C9: Afternoon | D9: 0.54166667 | E9: 0.6875 | F9: =ROUND((E9-D9)*24,2) -> 3.5 | G9: 1:00 to 2:00 English: Reading & vocabulary 2:15 to 3:15 English: Listening 3:30 to 4:30 IT lab: English practice | H9: English class + IT lab
A10: 12 | B10: 46336 | C10: Afternoon | D10: 0.54166667 | E10: 0.6875 | F10: =ROUND((E10-D10)*24,2) -> 3.5 | G10: 1:00 to 2:00 English: Reading & vocabulary 2:15 to 3:15 English: Listening 3:30 to 4:30 IT lab: English practice | H10: English class + IT lab
A11: 14 | B11: 46338 | C11: Afternoon | D11: 0.54166667 | E11: 0.6875 | F11: =ROUND((E11-D11)*24,2) -> 3.5 | G11: 1:00 to 2:00 Mid-programme English test: listening 2:15 to 4:30 Mid-programme test: speaking (one by one) + IT lab review | H11: Test / interview
A12: 17 | B12: 46341 | C12: Afternoon | D12: 0.54166667 | E12: 0.6875 | F12: =ROUND((E12-D12)*24,2) -> 3.5 | G12: 1:00 to 2:00 English: Reading & vocabulary 2:15 to 3:15 English: Listening 3:30 to 4:30 IT lab: English practice | H12: English class + IT lab
A13: 18 | B13: 46342 | C13: Afternoon | D13: 0.54166667 | E13: 0.6875 | F13: =ROUND((E13-D13)*24,2) -> 3.5 | G13: 1:00 to 2:30 English: Review & extra practice 2:45 to 3:30 English: Speaking practice in pairs 3:30 to 4:30 IT lab: English practice | H13: English class + IT lab
A14: 19 | B14: 46343 | C14: Afternoon | D14: 0.54166667 | E14: 0.6875 | F14: =ROUND((E14-D14)*24,2) -> 3.5 | G14: 1:00 to 2:00 English: Reading & vocabulary 2:15 to 3:15 English: Listening 3:30 to 4:30 IT lab: English practice | H14: English class + IT lab
A15: 22 | B15: 46346 | C15: Afternoon | D15: 0.54166667 | E15: 0.6875 | F15: =ROUND((E15-D15)*24,2) -> 3.5 | G15: 1:00 to 2:00 English: Reading & vocabulary 2:15 to 3:15 English: Listening 3:30 to 4:30 IT lab: English practice | H15: English class + IT lab
A16: 24 | B16: 46348 | C16: Afternoon | D16: 0.54166667 | E16: 0.6875 | F16: =ROUND((E16-D16)*24,2) -> 3.5 | G16: 1:00 to 2:00 English: Reading & vocabulary 2:15 to 3:15 English: Listening 3:30 to 4:30 IT lab: English practice | H16: English class + IT lab
A17: 25 | B17: 46349 | C17: Afternoon | D17: 0.54166667 | E17: 0.6875 | F17: =ROUND((E17-D17)*24,2) -> 3.5 | G17: 1:00 to 2:00 English: Reading & vocabulary 2:15 to 3:15 English: Listening 3:30 to 4:30 IT lab: English practice | H17: English class + IT lab
... A19: 28 | B19: 46352 | C19: Afternoon | D19: 0.54166667 | E19: 0.58333333 | F19: =ROUND((E19-D19)*24,2) -> 1 | G19: 1:00 to 2:00 Final English test: listening | H19: Test / interview

Sheet English Teacher 4 TBC
A1: English Teacher 4 (TBC)
A2: Cover teacher if someone cannot come · To be confirmed
A3: Sessions: | B3: =COUNT(A6:A6) -> 0 | D3: Hours: | E3: =SUM(F6:F6) -> 0 | G3: One row per session. Hours = start to finish, including the tea break.
A5: Day | B5: Date | C5: Session | D5: Start | E5: End | F5: Hours | G5: What happens in this session | H5: Type

Sheet Korean Teacher 1
A1: Korean Teacher 1
A2: Korean mornings (staff) · Confirmed
A3: Sessions: | B3: =COUNT(A6:A20) -> 15 | D3: Hours: | E3: =SUM(F6:F20) -> 45 | G3: One row per session. Hours = start to finish, including the tea break.
A5: Day | B5: Date | C5: Session | D5: Start | E5: End | F5: Hours | G5: What happens in this session | H5: Type
A6: 2 | B6: 46326 | C6: Morning | D6: 0.35416667 | E6: 0.47916667 | F6: =ROUND((E6-D6)*24,2) -> 3 | G6: 8:30 to 10:00 Korean: Hangul 1: alphabet warm-up + How Hangul works 10:15 to 11:30 Korean practice: Hangul 1: alphabet warm-up + How Hangul works | H6: Korean class
A7: 3 | B7: 46327 | C7: Morning | D7: 0.35416667 | E7: 0.47916667 | F7: =ROUND((E7-D7)*24,2) -> 3 | G7: 8:30 to 10:00 Korean: Hangul 3: The y-vowels 10:15 to 11:30 Korean practice: Hangul 3: The y-vowels | H7: Korean class
A8: 8 | B8: 46332 | C8: Morning | D8: 0.35416667 | E8: 0.47916667 | F8: =ROUND((E8-D8)*24,2) -> 3 | G8: 8:30 to 10:00 Korean: Review: Hangul 1 to 6 + writing practice 10:15 to 11:30 Korean practice: Review: Hangul 1 to 6 + writing practice | H8: Korean class
A9: 10 | B9: 46334 | C9: Morning | D9: 0.35416667 | E9: 0.47916667 | F9: =ROUND((E9-D9)*24,2) -> 3 | G9: 8:30 to 10:00 Korean: Hangul 8: Build and write blocks 10:15 to 11:30 Korean practice: Hangul 8: Build and write blocks | H9: Korean class
A10: 11 | B10: 46335 | C10: Morning | D10: 0.35416667 | E10: 0.47916667 | F10: =ROUND((E10-D10)*24,2) -> 3 | G10: 8:30 to 10:00 Korean: Hangul 9: Final consonants: batchim 10:15 to 11:30 Korean practice: Hangul 9: Final consonants: batchim | H10: Korean class
A11: 12 | B11: 46336 | C11: Morning | D11: 0.35416667 | E11: 0.47916667 | F11: =ROUND((E11-D11)*24,2) -> 3 | G11: 8:30 to 10:00 Korean: Hangul 10: Link sounds between blocks 10:15 to 11:30 Korean practice: Hangul 10: Link sounds between blocks | H11: Korean class
A12: 15 | B12: 46339 | C12: Morning | D12: 0.35416667 | E12: 0.47916667 | F12: =ROUND((E12-D12)*24,2) -> 3 | G12: 8:30 to 10:00 Korean: Hangul 12: Read words and sentences 10:15 to 11:30 Korean practice: Hangul 12: Read words and sentences | H12: Korean class
A13: 17 | B13: 46341 | C13: Morning | D13: 0.35416667 | E13: 0.47916667 | F13: =ROUND((E13-D13)*24,2) -> 3 | G13: 8:30 to 10:00 Korean: Beginner 1 lesson 2: What is this? 10:15 to 11:30 Korean practice: Beginner 1 lesson 2: What is this? | H13: Korean class
A14: 18 | B14: 46342 | C14: Morning | D14: 0.35416667 | E14: 0.47916667 | F14: =ROUND((E14-D14)*24,2) -> 3 | G14: 8:30 to 10:00 Korean: Beginner 1 lesson 3: Where is it? 10:15 to 11:30 Korean practice: Beginner 1 lesson 3: Where is it? | H14: Korean class
A15: 19 | B15: 46343 | C15: Morning | D15: 0.35416667 | E15: 0.47916667 | F15: =ROUND((E15-D15)*24,2) -> 3 | G15: 8:30 to 10:00 Korean: Beginner 1 lesson 4: My everyday actions 10:15 to 11:30 Korean practice: Beginner 1 lesson 4: My everyday actions | H15: Korean class
A16: 22 | B16: 46346 | C16: Morning | D16: 0.35416667 | E16: 0.47916667 | F16: =ROUND((E16-D16)*24,2) -> 3 | G16: 8:30 to 10:00 Korean: Review: Beginner 1 lessons 1 to 6 10:15 to 11:30 Korean practice: Review: Beginner 1 lessons 1 to 6 | H16: Korean class
A17: 24 | B17: 46348 | C17: Morning | D17: 0.35416667 | E17: 0.47916667 | F17: =ROUND((E17-D17)*24,2) -> 3 | G17: 8:30 to 10:00 Korean: Beginner 1 lesson 8: Time & routines 10:15 to 11:30 Korean practice: Beginner 1 lesson 8: Time & routines | H17: Korean class
... A20: 29 | B20: 46353 | C20: Morning | D20: 0.35416667 | E20: 0.47916667 | F20: =ROUND((E20-D20)*24,2) -> 3 | G20: 8:30 to 10:00 Korean: Beginner 1 lesson 12: Put it all together 10:15 to 11:30 Korean practice: Beginner 1 lesson 12: Put it all together | H20: Korean class

Sheet Korean Teacher 2
A1: Korean Teacher 2
A2: Korean afternoons & Korean IT lab (staff) · Confirmed
A3: Sessions: | B3: =COUNT(A6:A19) -> 14 | D3: Hours: | E3: =SUM(F6:F19) -> 49 | G3: One row per session. Hours = start to finish, including the tea break.
A5: Day | B5: Date | C5: Session | D5: Start | E5: End | F5: Hours | G5: What happens in this session | H5: Type
A6: 2 | B6: 46326 | C6: Afternoon | D6: 0.54166667 | E6: 0.6875 | F6: =ROUND((E6-D6)*24,2) -> 3.5 | G6: 1:00 to 2:30 Korean: Hangul 2: Six starting vowels 2:45 to 3:30 Korean practice: Hangul 2: Six starting vowels 3:30 to 4:30 IT lab: Korean practice | H6: IT lab + Korean class
A7: 3 | B7: 46327 | C7: Afternoon | D7: 0.54166667 | E7: 0.6875 | F7: =ROUND((E7-D7)*24,2) -> 3.5 | G7: 1:00 to 2:30 Korean: Hangul 4: Nine starting consonants 2:45 to 3:30 Korean practice: Hangul 4: Nine starting consonants 3:30 to 4:30 IT lab: Korean practice | H7: IT lab + Korean class
A8: 6 | B8: 46330 | C8: Afternoon | D8: 0.54166667 | E8: 0.6875 | F8: =ROUND((E8-D8)*24,2) -> 3.5 | G8: 1:00 to 2:30 Korean: Hangul 5: Air and consonants 2:45 to 3:30 Korean practice: Hangul 5: Air and consonants 3:30 to 4:30 IT lab: Korean practice | H8: IT lab + Korean class
A9: 7 | B9: 46331 | C9: Afternoon | D9: 0.54166667 | E9: 0.6875 | F9: =ROUND((E9-D9)*24,2) -> 3.5 | G9: 1:00 to 2:30 Korean: Hangul 6: Tense consonants 2:45 to 3:30 Korean practice: Hangul 6: Tense consonants 3:30 to 4:30 IT lab: Korean practice | H9: IT lab + Korean class
A10: 9 | B10: 46333 | C10: Afternoon | D10: 0.54166667 | E10: 0.6875 | F10: =ROUND((E10-D10)*24,2) -> 3.5 | G10: 1:00 to 2:30 Korean: Hangul 7: Eleven more vowels 2:45 to 3:30 Korean practice: Hangul 7: Eleven more vowels 3:30 to 4:30 IT lab: Korean practice | H10: IT lab + Korean class
A11: 13 | B11: 46337 | C11: Afternoon | D11: 0.54166667 | E11: 0.6875 | F11: =ROUND((E11-D11)*24,2) -> 3.5 | G11: 1:00 to 2:30 Korean: Hangul 11: Double finals and sound changes 2:45 to 3:30 Korean practice: Hangul 11: Double finals and sound changes 3:30 to 4:30 IT lab: Korean practice | H11: IT lab + Korean class
A12: 15 | B12: 46339 | C12: Afternoon | D12: 0.54166667 | E12: 0.6875 | F12: =ROUND((E12-D12)*24,2) -> 3.5 | G12: 1:00 to 2:30 Korean: Mid-programme Korean check (Hangul) 2:45 to 3:30 Mid-programme Korean check (Hangul) (continued) 3:30 to 4:30 IT lab: Korean practice | H12: IT lab + Test / interview
A13: 16 | B13: 46340 | C13: Afternoon | D13: 0.54166667 | E13: 0.6875 | F13: =ROUND((E13-D13)*24,2) -> 3.5 | G13: 1:00 to 2:30 Korean: Beginner 1 lesson 1: Greetings & introductions 2:45 to 3:30 Korean practice: Beginner 1 lesson 1: Greetings & introductions 3:30 to 4:30 IT lab: Korean practice | H13: IT lab + Korean class
A14: 20 | B14: 46344 | C14: Afternoon | D14: 0.54166667 | E14: 0.6875 | F14: =ROUND((E14-D14)*24,2) -> 3.5 | G14: 1:00 to 2:30 Korean: Beginner 1 lesson 5: Places & going out 2:45 to 3:30 Korean practice: Beginner 1 lesson 5: Places & going out 3:30 to 4:30 IT lab: Korean practice | H14: IT lab + Korean class
A15: 21 | B15: 46345 | C15: Afternoon | D15: 0.54166667 | E15: 0.6875 | F15: =ROUND((E15-D15)*24,2) -> 3.5 | G15: 1:00 to 2:30 Korean: Beginner 1 lesson 6: Numbers & prices 2:45 to 3:30 Korean practice: Beginner 1 lesson 6: Numbers & prices 3:30 to 4:30 IT lab: Korean practice | H15: IT lab + Korean class
A16: 23 | B16: 46347 | C16: Afternoon | D16: 0.54166667 | E16: 0.6875 | F16: =ROUND((E16-D16)*24,2) -> 3.5 | G16: 1:00 to 2:30 Korean: Beginner 1 lesson 7: Shopping & quantities 2:45 to 3:30 Korean practice: Beginner 1 lesson 7: Shopping & quantities 3:30 to 4:30 IT lab: Korean practice | H16: IT lab + Korean class
A17: 27 | B17: 46351 | C17: Afternoon | D17: 0.54166667 | E17: 0.6875 | F17: =ROUND((E17-D17)*24,2) -> 3.5 | G17: 1:00 to 2:30 Korean: Beginner 1 lesson 11: What I want to do 2:45 to 3:30 Korean practice: Beginner 1 lesson 11: What I want to do 3:30 to 4:30 IT lab: Korean practice | H17: IT lab + Korean class
... A19: 30 | B19: 46354 | C19: Afternoon | D19: 0.54166667 | E19: 0.6875 | F19: =ROUND((E19-D19)*24,2) -> 3.5 | G19: 1:00 to 2:30 Korean: Korean self-introduction (graduation speech practice) 2:45 to 3:30 Korean practice: Korean self-introduction (graduation speech practice) 3:30 to 4:30 IT lab: Korean practice | H19: IT lab + Korean class
